[
    {
        "name": "The End of Anubis",
        "passcode": 65403020,
        "konami_id": 6073,
        "wikilink": "https://yugipedia.com/wiki/AST-AE000",
        "set_number": "AST-AE000",
        "set_name": "Ancient Sanctuary",
        "rarity": "Secret Rare",
        "date_release": "14 OCTOBER 2004"
    },
    {
        "name": "Gogiga Gagagigo",
        "passcode": 39674352,
        "konami_id": 5946,
        "wikilink": "https://yugipedia.com/wiki/AST-AE001",
        "set_number": "AST-AE001",
        "set_name": "Ancient Sanctuary",
        "rarity": "Common",
        "date_release": "14 OCTOBER 2004"
    },
    {
        "name": "Warrior of Zera",
        "passcode": 66073051,
        "konami_id": 5947,
        "wikilink": "https://yugipedia.com/wiki/AST-AE002",
        "set_number": "AST-AE002",
        "set_name": "Ancient Sanctuary",
        "rarity": "Common",
        "date_release": "14 OCTOBER 2004"
    },
    {
        "name": "Sealmaster Meisei",
        "passcode": 2468169,
        "konami_id": 5948,
        "wikilink": "https://yugipedia.com/wiki/AST-AE003",
        "set_number": "AST-AE003",
        "set_name": "Ancient Sanctuary",
        "rarity": "Rare",
        "date_release": "14 OCTOBER 2004"
    },
    {
        "name": "Mystical Shine Ball",
        "passcode": 39552864,
        "konami_id": 5949,
        "wikilink": "https://yugipedia.com/wiki/AST-AE004",
        "set_number": "AST-AE004",
        "set_name": "Ancient Sanctuary",
        "rarity": "Common",
        "date_release": "14 OCTOBER 2004"
    },
    {
        "name": "Metal Armored Bug",
        "passcode": 65957473,
        "konami_id": 5950,
        "wikilink": "https://yugipedia.com/wiki/AST-AE005",
        "set_number": "AST-AE005",
        "set_name": "Ancient Sanctuary",
        "rarity": "Common",
        "date_release": "14 OCTOBER 2004"
    },
    {
        "name": "The Agent of Judgment - Saturn",
        "passcode": 91345518,
        "konami_id": 5951,
        "wikilink": "https://yugipedia.com/wiki/AST-AE006",
        "set_number": "AST-AE006",
        "set_name": "Ancient Sanctuary",
        "rarity": "Ultra Rare",
        "date_release": "14 OCTOBER 2004"
    },
    {
        "name": "The Agent of Wisdom - Mercury",
        "passcode": 38730226,
        "konami_id": 5952,
        "wikilink": "https://yugipedia.com/wiki/AST-AE007",
        "set_number": "AST-AE007",
        "set_name": "Ancient Sanctuary",
        "rarity": "Rare",
        "date_release": "14 OCTOBER 2004"
    },
    {
        "name": "The Agent of Creation - Venus",
        "passcode": 64734921,
        "konami_id": 5953,
        "wikilink": "https://yugipedia.com/wiki/AST-AE008",
        "set_number": "AST-AE008",
        "set_name": "Ancient Sanctuary",
        "rarity": "Rare",
        "date_release": "14 OCTOBER 2004"
    },
    {
        "name": "The Agent of Force - Mars",
        "passcode": 91123920,
        "konami_id": 5954,
        "wikilink": "https://yugipedia.com/wiki/AST-AE009",
        "set_number": "AST-AE009",
        "set_name": "Ancient Sanctuary",
        "rarity": "Super Rare",
        "date_release": "14 OCTOBER 2004"
    },
    {
        "name": "The Unhappy Girl",
        "passcode": 27618634,
        "konami_id": 5955,
        "wikilink": "https://yugipedia.com/wiki/AST-AE010",
        "set_number": "AST-AE010",
        "set_name": "Ancient Sanctuary",
        "rarity": "Common",
        "date_release": "14 OCTOBER 2004"
    },
    {
        "name": "Soul-Absorbing Bone Tower",
        "passcode": 63012333,
        "konami_id": 5956,
        "wikilink": "https://yugipedia.com/wiki/AST-AE011",
        "set_number": "AST-AE011",
        "set_name": "Ancient Sanctuary",
        "rarity": "Rare",
        "date_release": "14 OCTOBER 2004"
    },
    {
        "name": "The Kick Man",
        "passcode": 90407382,
        "konami_id": 5957,
        "wikilink": "https://yugipedia.com/wiki/AST-AE012",
        "set_number": "AST-AE012",
        "set_name": "Ancient Sanctuary",
        "rarity": "Common",
        "date_release": "14 OCTOBER 2004"
    },
    {
        "name": "Vampire Lady",
        "passcode": 26495087,
        "konami_id": 5958,
        "wikilink": "https://yugipedia.com/wiki/AST-AE013",
        "set_number": "AST-AE013",
        "set_name": "Ancient Sanctuary",
        "rarity": "Common",
        "date_release": "14 OCTOBER 2004"
    },
    {
        "name": "Stone Statue of the Aztecs",
        "passcode": 31812496,
        "konami_id": 4754,
        "wikilink": "https://yugipedia.com/wiki/AST-AE014",
        "set_number": "AST-AE014",
        "set_name": "Ancient Sanctuary",
        "rarity": "Super Rare",
        "date_release": "14 OCTOBER 2004"
    },
    {
        "name": "Rocket Jumper",
        "passcode": 53890795,
        "konami_id": 5959,
        "wikilink": "https://yugipedia.com/wiki/AST-AE015",
        "set_number": "AST-AE015",
        "set_name": "Ancient Sanctuary",
        "rarity": "Common",
        "date_release": "14 OCTOBER 2004"
    },
    {
        "name": "Avatar of The Pot",
        "passcode": 99284890,
        "konami_id": 5960,
        "wikilink": "https://yugipedia.com/wiki/AST-AE016",
        "set_number": "AST-AE016",
        "set_name": "Ancient Sanctuary",
        "rarity": "Rare",
        "date_release": "14 OCTOBER 2004"
    },
    {
        "name": "Legendary Jujitsu Master",
        "passcode": 25773409,
        "konami_id": 5961,
        "wikilink": "https://yugipedia.com/wiki/AST-AE017",
        "set_number": "AST-AE017",
        "set_name": "Ancient Sanctuary",
        "rarity": "Common",
        "date_release": "14 OCTOBER 2004"
    },
    {
        "name": "Gear Golem the Moving Fortress",
        "passcode": 30190809,
        "konami_id": 4757,
        "wikilink": "https://yugipedia.com/wiki/AST-AE018",
        "set_number": "AST-AE018",
        "set_name": "Ancient Sanctuary",
        "rarity": "Ultra Rare",
        "date_release": "14 OCTOBER 2004"
    },
    {
        "name": "KA-2 Des Scissors",
        "passcode": 52768103,
        "konami_id": 5962,
        "wikilink": "https://yugipedia.com/wiki/AST-AE019",
        "set_number": "AST-AE019",
        "set_name": "Ancient Sanctuary",
        "rarity": "Common",
        "date_release": "14 OCTOBER 2004"
    },
    {
        "name": "Needle Burrower",
        "passcode": 98162242,
        "konami_id": 5963,
        "wikilink": "https://yugipedia.com/wiki/AST-AE020",
        "set_number": "AST-AE020",
        "set_name": "Ancient Sanctuary",
        "rarity": "Super Rare",
        "date_release": "14 OCTOBER 2004"
    },
    {
        "name": "Sonic Jammer",
        "passcode": 84550200,
        "konami_id": 5053,
        "wikilink": "https://yugipedia.com/wiki/AST-AE021",
        "set_number": "AST-AE021",
        "set_name": "Ancient Sanctuary",
        "rarity": "Common",
        "date_release": "14 OCTOBER 2004"
    },
    {
        "name": "Blowback Dragon",
        "passcode": 25551951,
        "konami_id": 5964,
        "wikilink": "https://yugipedia.com/wiki/AST-AE022",
        "set_number": "AST-AE022",
        "set_name": "Ancient Sanctuary",
        "rarity": "Ultra Rare",
        "date_release": "14 OCTOBER 2004"
    },
    {
        "name": "Zaborg the Thunder Monarch",
        "passcode": 51945556,
        "konami_id": 5965,
        "wikilink": "https://yugipedia.com/wiki/AST-AE023",
        "set_number": "AST-AE023",
        "set_name": "Ancient Sanctuary",
        "rarity": "Super Rare",
        "date_release": "14 OCTOBER 2004"
    },
    {
        "name": "Atomic Firefly",
        "passcode": 87340664,
        "konami_id": 5966,
        "wikilink": "https://yugipedia.com/wiki/AST-AE024",
        "set_number": "AST-AE024",
        "set_name": "Ancient Sanctuary",
        "rarity": "Common",
        "date_release": "14 OCTOBER 2004"
    },
    {
        "name": "Mermaid Knight",
        "passcode": 24435369,
        "konami_id": 5967,
        "wikilink": "https://yugipedia.com/wiki/AST-AE025",
        "set_number": "AST-AE025",
        "set_name": "Ancient Sanctuary",
        "rarity": "Common",
        "date_release": "14 OCTOBER 2004"
    },
    {
        "name": "Piranha Army",
        "passcode": 50823978,
        "konami_id": 5968,
        "wikilink": "https://yugipedia.com/wiki/AST-AE026",
        "set_number": "AST-AE026",
        "set_name": "Ancient Sanctuary",
        "rarity": "Common",
        "date_release": "14 OCTOBER 2004"
    },
    {
        "name": "Two Thousand Needles",
        "passcode": 83228073,
        "konami_id": 5969,
        "wikilink": "https://yugipedia.com/wiki/AST-AE027",
        "set_number": "AST-AE027",
        "set_name": "Ancient Sanctuary",
        "rarity": "Common",
        "date_release": "14 OCTOBER 2004"
    },
    {
        "name": "Disc Fighter",
        "passcode": 19612721,
        "konami_id": 5970,
        "wikilink": "https://yugipedia.com/wiki/AST-AE028",
        "set_number": "AST-AE028",
        "set_name": "Ancient Sanctuary",
        "rarity": "Common",
        "date_release": "14 OCTOBER 2004"
    },
    {
        "name": "Arcane Archer of the Forest",
        "passcode": 55001420,
        "konami_id": 5971,
        "wikilink": "https://yugipedia.com/wiki/AST-AE029",
        "set_number": "AST-AE029",
        "set_name": "Ancient Sanctuary",
        "rarity": "Common",
        "date_release": "14 OCTOBER 2004"
    },
    {
        "name": "Lady Ninja Yae",
        "passcode": 82005435,
        "konami_id": 5972,
        "wikilink": "https://yugipedia.com/wiki/AST-AE030",
        "set_number": "AST-AE030",
        "set_name": "Ancient Sanctuary",
        "rarity": "Common",
        "date_release": "14 OCTOBER 2004"
    },
    {
        "name": "Goblin King",
        "passcode": 18590133,
        "konami_id": 5973,
        "wikilink": "https://yugipedia.com/wiki/AST-AE031",
        "set_number": "AST-AE031",
        "set_name": "Ancient Sanctuary",
        "rarity": "Common",
        "date_release": "14 OCTOBER 2004"
    },
    {
        "name": "Solar Flare Dragon",
        "passcode": 45985838,
        "konami_id": 5974,
        "wikilink": "https://yugipedia.com/wiki/AST-AE032",
        "set_number": "AST-AE032",
        "set_name": "Ancient Sanctuary",
        "rarity": "Common",
        "date_release": "14 OCTOBER 2004"
    },
    {
        "name": "White Magician Pikeru",
        "passcode": 81383947,
        "konami_id": 5975,
        "wikilink": "https://yugipedia.com/wiki/AST-AE033",
        "set_number": "AST-AE033",
        "set_name": "Ancient Sanctuary",
        "rarity": "Common",
        "date_release": "14 OCTOBER 2004"
    },
    {
        "name": "Archlord Zerato",
        "passcode": 18378582,
        "konami_id": 5976,
        "wikilink": "https://yugipedia.com/wiki/AST-AE034",
        "set_number": "AST-AE034",
        "set_name": "Ancient Sanctuary",
        "rarity": "Ultra Rare",
        "date_release": "14 OCTOBER 2004"
    },
    {
        "name": "Opti-Camouflage Armor",
        "passcode": 44762290,
        "konami_id": 5977,
        "wikilink": "https://yugipedia.com/wiki/AST-AE035",
        "set_number": "AST-AE035",
        "set_name": "Ancient Sanctuary",
        "rarity": "Common",
        "date_release": "14 OCTOBER 2004"
    },
    {
        "name": "Mystik Wok",
        "passcode": 80161395,
        "konami_id": 5978,
        "wikilink": "https://yugipedia.com/wiki/AST-AE036",
        "set_number": "AST-AE036",
        "set_name": "Ancient Sanctuary",
        "rarity": "Common",
        "date_release": "14 OCTOBER 2004"
    },
    {
        "name": "Enemy Controller",
        "passcode": 98045062,
        "konami_id": 5505,
        "wikilink": "https://yugipedia.com/wiki/AST-AE037",
        "set_number": "AST-AE037",
        "set_name": "Ancient Sanctuary",
        "rarity": "Ultra Rare",
        "date_release": "14 OCTOBER 2004"
    },
    {
        "name": "Burst Stream of Destruction",
        "passcode": 17655904,
        "konami_id": 5979,
        "wikilink": "https://yugipedia.com/wiki/AST-AE038",
        "set_number": "AST-AE038",
        "set_name": "Ancient Sanctuary",
        "rarity": "Ultra Rare",
        "date_release": "14 OCTOBER 2004"
    },
    {
        "name": "Monster Gate",
        "passcode": 43040603,
        "konami_id": 5980,
        "wikilink": "https://yugipedia.com/wiki/AST-AE039",
        "set_number": "AST-AE039",
        "set_name": "Ancient Sanctuary",
        "rarity": "Common",
        "date_release": "14 OCTOBER 2004"
    },
    {
        "name": "Amplifier",
        "passcode": 303660,
        "konami_id": 4819,
        "wikilink": "https://yugipedia.com/wiki/AST-AE040",
        "set_number": "AST-AE040",
        "set_name": "Ancient Sanctuary",
        "rarity": "Super Rare",
        "date_release": "14 OCTOBER 2004"
    },
    {
        "name": "Weapon Change",
        "passcode": 10035717,
        "konami_id": 5981,
        "wikilink": "https://yugipedia.com/wiki/AST-AE041",
        "set_number": "AST-AE041",
        "set_name": "Ancient Sanctuary",
        "rarity": "Common",
        "date_release": "14 OCTOBER 2004"
    },
    {
        "name": "The Sanctuary in the Sky",
        "passcode": 56433456,
        "konami_id": 5982,
        "wikilink": "https://yugipedia.com/wiki/AST-AE042",
        "set_number": "AST-AE042",
        "set_name": "Ancient Sanctuary",
        "rarity": "Super Rare",
        "date_release": "14 OCTOBER 2004"
    },
    {
        "name": "Earthquake",
        "passcode": 82828051,
        "konami_id": 5983,
        "wikilink": "https://yugipedia.com/wiki/AST-AE043",
        "set_number": "AST-AE043",
        "set_name": "Ancient Sanctuary",
        "rarity": "Common",
        "date_release": "14 OCTOBER 2004"
    },
    {
        "name": "Talisman of Trap Sealing",
        "passcode": 19312169,
        "konami_id": 5984,
        "wikilink": "https://yugipedia.com/wiki/AST-AE044",
        "set_number": "AST-AE044",
        "set_name": "Ancient Sanctuary",
        "rarity": "Rare",
        "date_release": "14 OCTOBER 2004"
    },
    {
        "name": "Goblin Thief",
        "passcode": 45311864,
        "konami_id": 5985,
        "wikilink": "https://yugipedia.com/wiki/AST-AE045",
        "set_number": "AST-AE045",
        "set_name": "Ancient Sanctuary",
        "rarity": "Common",
        "date_release": "14 OCTOBER 2004"
    },
    {
        "name": "Backfire",
        "passcode": 82705573,
        "konami_id": 5986,
        "wikilink": "https://yugipedia.com/wiki/AST-AE046",
        "set_number": "AST-AE046",
        "set_name": "Ancient Sanctuary",
        "rarity": "Common",
        "date_release": "14 OCTOBER 2004"
    },
    {
        "name": "Micro Ray",
        "passcode": 18190572,
        "konami_id": 5987,
        "wikilink": "https://yugipedia.com/wiki/AST-AE047",
        "set_number": "AST-AE047",
        "set_name": "Ancient Sanctuary",
        "rarity": "Common",
        "date_release": "14 OCTOBER 2004"
    },
    {
        "name": "Light of Judgment",
        "passcode": 44595286,
        "konami_id": 5988,
        "wikilink": "https://yugipedia.com/wiki/AST-AE048",
        "set_number": "AST-AE048",
        "set_name": "Ancient Sanctuary",
        "rarity": "Common",
        "date_release": "14 OCTOBER 2004"
    },
    {
        "name": "Talisman of Spell Sealing",
        "passcode": 71983925,
        "konami_id": 5989,
        "wikilink": "https://yugipedia.com/wiki/AST-AE049",
        "set_number": "AST-AE049",
        "set_name": "Ancient Sanctuary",
        "rarity": "Rare",
        "date_release": "14 OCTOBER 2004"
    },
    {
        "name": "Wall of Revealing Light",
        "passcode": 17078030,
        "konami_id": 5990,
        "wikilink": "https://yugipedia.com/wiki/AST-AE050",
        "set_number": "AST-AE050",
        "set_name": "Ancient Sanctuary",
        "rarity": "Common",
        "date_release": "14 OCTOBER 2004"
    },
    {
        "name": "Solar Ray",
        "passcode": 44472639,
        "konami_id": 5991,
        "wikilink": "https://yugipedia.com/wiki/AST-AE051",
        "set_number": "AST-AE051",
        "set_name": "Ancient Sanctuary",
        "rarity": "Common",
        "date_release": "14 OCTOBER 2004"
    },
    {
        "name": "Ninjitsu Art of Transformation",
        "passcode": 70861343,
        "konami_id": 5992,
        "wikilink": "https://yugipedia.com/wiki/AST-AE052",
        "set_number": "AST-AE052",
        "set_name": "Ancient Sanctuary",
        "rarity": "Common",
        "date_release": "14 OCTOBER 2004"
    },
    {
        "name": "Beckoning Light",
        "passcode": 16255442,
        "konami_id": 5993,
        "wikilink": "https://yugipedia.com/wiki/AST-AE053",
        "set_number": "AST-AE053",
        "set_name": "Ancient Sanctuary",
        "rarity": "Common",
        "date_release": "14 OCTOBER 2004"
    },
    {
        "name": "Draining Shield",
        "passcode": 43250041,
        "konami_id": 5994,
        "wikilink": "https://yugipedia.com/wiki/AST-AE054",
        "set_number": "AST-AE054",
        "set_name": "Ancient Sanctuary",
        "rarity": "Rare",
        "date_release": "14 OCTOBER 2004"
    },
    {
        "name": "Armor Break",
        "passcode": 79649195,
        "konami_id": 5995,
        "wikilink": "https://yugipedia.com/wiki/AST-AE055",
        "set_number": "AST-AE055",
        "set_name": "Ancient Sanctuary",
        "rarity": "Common",
        "date_release": "14 OCTOBER 2004"
    },
    {
        "name": "Gigobyte",
        "passcode": 53776525,
        "konami_id": 6019,
        "wikilink": "https://yugipedia.com/wiki/AST-AE056",
        "set_number": "AST-AE056",
        "set_name": "Ancient Sanctuary",
        "rarity": "Common",
        "date_release": "14 OCTOBER 2004"
    },
    {
        "name": "Mokey Mokey",
        "passcode": 27288416,
        "konami_id": 6018,
        "wikilink": "https://yugipedia.com/wiki/AST-AE057",
        "set_number": "AST-AE057",
        "set_name": "Ancient Sanctuary",
        "rarity": "Common",
        "date_release": "14 OCTOBER 2004"
    },
    {
        "name": "Kozaky",
        "passcode": 99171160,
        "konami_id": 6020,
        "wikilink": "https://yugipedia.com/wiki/AST-AE058",
        "set_number": "AST-AE058",
        "set_name": "Ancient Sanctuary",
        "rarity": "Common",
        "date_release": "14 OCTOBER 2004"
    },
    {
        "name": "Fiend Scorpion",
        "passcode": 26566878,
        "konami_id": 6021,
        "wikilink": "https://yugipedia.com/wiki/AST-AE059",
        "set_number": "AST-AE059",
        "set_name": "Ancient Sanctuary",
        "rarity": "Common",
        "date_release": "14 OCTOBER 2004"
    },
    {
        "name": "Pharaoh's Servant",
        "passcode": 52550973,
        "konami_id": 6022,
        "wikilink": "https://yugipedia.com/wiki/AST-AE060",
        "set_number": "AST-AE060",
        "set_name": "Ancient Sanctuary",
        "rarity": "Common",
        "date_release": "14 OCTOBER 2004"
    },
    {
        "name": "Pharaonic Protector",
        "passcode": 89959682,
        "konami_id": 6023,
        "wikilink": "https://yugipedia.com/wiki/AST-AE061",
        "set_number": "AST-AE061",
        "set_name": "Ancient Sanctuary",
        "rarity": "Common",
        "date_release": "14 OCTOBER 2004"
    },
    {
        "name": "Spirit of the Pharaoh",
        "passcode": 25343280,
        "konami_id": 6024,
        "wikilink": "https://yugipedia.com/wiki/AST-AE062",
        "set_number": "AST-AE062",
        "set_name": "Ancient Sanctuary",
        "rarity": "Ultra Rare",
        "date_release": "14 OCTOBER 2004"
    },
    {
        "name": "Theban Nightmare",
        "passcode": 51838385,
        "konami_id": 6025,
        "wikilink": "https://yugipedia.com/wiki/AST-AE063",
        "set_number": "AST-AE063",
        "set_name": "Ancient Sanctuary",
        "rarity": "Rare",
        "date_release": "14 OCTOBER 2004"
    },
    {
        "name": "Aswan Apparition",
        "passcode": 88236094,
        "konami_id": 6026,
        "wikilink": "https://yugipedia.com/wiki/AST-AE064",
        "set_number": "AST-AE064",
        "set_name": "Ancient Sanctuary",
        "rarity": "Common",
        "date_release": "14 OCTOBER 2004"
    },
    {
        "name": "Protector of the Sanctuary",
        "passcode": 24221739,
        "konami_id": 6027,
        "wikilink": "https://yugipedia.com/wiki/AST-AE065",
        "set_number": "AST-AE065",
        "set_name": "Ancient Sanctuary",
        "rarity": "Common",
        "date_release": "14 OCTOBER 2004"
    },
    {
        "name": "Nubian Guard",
        "passcode": 51616747,
        "konami_id": 6028,
        "wikilink": "https://yugipedia.com/wiki/AST-AE066",
        "set_number": "AST-AE066",
        "set_name": "Ancient Sanctuary",
        "rarity": "Common",
        "date_release": "14 OCTOBER 2004"
    },
    {
        "name": "Legacy Hunter",
        "passcode": 87010442,
        "konami_id": 6029,
        "wikilink": "https://yugipedia.com/wiki/AST-AE067",
        "set_number": "AST-AE067",
        "set_name": "Ancient Sanctuary",
        "rarity": "Super Rare",
        "date_release": "14 OCTOBER 2004"
    },
    {
        "name": "Desertapir",
        "passcode": 13409151,
        "konami_id": 6030,
        "wikilink": "https://yugipedia.com/wiki/AST-AE068",
        "set_number": "AST-AE068",
        "set_name": "Ancient Sanctuary",
        "rarity": "Common",
        "date_release": "14 OCTOBER 2004"
    },
    {
        "name": "Sand Gambler",
        "passcode": 50593156,
        "konami_id": 6031,
        "wikilink": "https://yugipedia.com/wiki/AST-AE069",
        "set_number": "AST-AE069",
        "set_name": "Ancient Sanctuary",
        "rarity": "Common",
        "date_release": "14 OCTOBER 2004"
    },
    {
        "name": "3-Hump Lacooda",
        "passcode": 86988864,
        "konami_id": 6032,
        "wikilink": "https://yugipedia.com/wiki/AST-AE070",
        "set_number": "AST-AE070",
        "set_name": "Ancient Sanctuary",
        "rarity": "Common",
        "date_release": "14 OCTOBER 2004"
    },
    {
        "name": "Ghost Knight of Jackal",
        "passcode": 13386503,
        "konami_id": 6033,
        "wikilink": "https://yugipedia.com/wiki/AST-AE071",
        "set_number": "AST-AE071",
        "set_name": "Ancient Sanctuary",
        "rarity": "Ultra Rare",
        "date_release": "14 OCTOBER 2004"
    },
    {
        "name": "Absorbing Kid from the Sky",
        "passcode": 49771608,
        "konami_id": 6034,
        "wikilink": "https://yugipedia.com/wiki/AST-AE072",
        "set_number": "AST-AE072",
        "set_name": "Ancient Sanctuary",
        "rarity": "Common",
        "date_release": "14 OCTOBER 2004"
    },
    {
        "name": "Elephant Statue of Blessing",
        "passcode": 85166216,
        "konami_id": 6035,
        "wikilink": "https://yugipedia.com/wiki/AST-AE073",
        "set_number": "AST-AE073",
        "set_name": "Ancient Sanctuary",
        "rarity": "Common",
        "date_release": "14 OCTOBER 2004"
    },
    {
        "name": "Elephant Statue of Disaster",
        "passcode": 12160911,
        "konami_id": 6036,
        "wikilink": "https://yugipedia.com/wiki/AST-AE074",
        "set_number": "AST-AE074",
        "set_name": "Ancient Sanctuary",
        "rarity": "Common",
        "date_release": "14 OCTOBER 2004"
    },
    {
        "name": "Spirit Caller",
        "passcode": 48659020,
        "konami_id": 6037,
        "wikilink": "https://yugipedia.com/wiki/AST-AE075",
        "set_number": "AST-AE075",
        "set_name": "Ancient Sanctuary",
        "rarity": "Common",
        "date_release": "14 OCTOBER 2004"
    },
    {
        "name": "Emissary of the Afterlife",
        "passcode": 75043725,
        "konami_id": 6038,
        "wikilink": "https://yugipedia.com/wiki/AST-AE076",
        "set_number": "AST-AE076",
        "set_name": "Ancient Sanctuary",
        "rarity": "Super Rare",
        "date_release": "14 OCTOBER 2004"
    },
    {
        "name": "Grave Protector",
        "passcode": 11448373,
        "konami_id": 6039,
        "wikilink": "https://yugipedia.com/wiki/AST-AE077",
        "set_number": "AST-AE077",
        "set_name": "Ancient Sanctuary",
        "rarity": "Rare",
        "date_release": "14 OCTOBER 2004"
    },
    {
        "name": "Double Coston",
        "passcode": 44436472,
        "konami_id": 6040,
        "wikilink": "https://yugipedia.com/wiki/AST-AE078",
        "set_number": "AST-AE078",
        "set_name": "Ancient Sanctuary",
        "rarity": "Rare",
        "date_release": "14 OCTOBER 2004"
    },
    {
        "name": "Regenerating Mummy",
        "passcode": 70821187,
        "konami_id": 6041,
        "wikilink": "https://yugipedia.com/wiki/AST-AE079",
        "set_number": "AST-AE079",
        "set_name": "Ancient Sanctuary",
        "rarity": "Common",
        "date_release": "14 OCTOBER 2004"
    },
    {
        "name": "Night Assailant",
        "passcode": 16226786,
        "konami_id": 6042,
        "wikilink": "https://yugipedia.com/wiki/AST-AE080",
        "set_number": "AST-AE080",
        "set_name": "Ancient Sanctuary",
        "rarity": "Common",
        "date_release": "14 OCTOBER 2004"
    },
    {
        "name": "Man-Thro' Tro'",
        "passcode": 43714890,
        "konami_id": 6043,
        "wikilink": "https://yugipedia.com/wiki/AST-AE081",
        "set_number": "AST-AE081",
        "set_name": "Ancient Sanctuary",
        "rarity": "Common",
        "date_release": "14 OCTOBER 2004"
    },
    {
        "name": "King of the Swamp",
        "passcode": 79109599,
        "konami_id": 6044,
        "wikilink": "https://yugipedia.com/wiki/AST-AE082",
        "set_number": "AST-AE082",
        "set_name": "Ancient Sanctuary",
        "rarity": "Rare",
        "date_release": "14 OCTOBER 2004"
    },
    {
        "name": "Emissary of the Oasis",
        "passcode": 6103294,
        "konami_id": 6045,
        "wikilink": "https://yugipedia.com/wiki/AST-AE083",
        "set_number": "AST-AE083",
        "set_name": "Ancient Sanctuary",
        "rarity": "Common",
        "date_release": "14 OCTOBER 2004"
    },
    {
        "name": "Special Hurricane",
        "passcode": 42598242,
        "konami_id": 6046,
        "wikilink": "https://yugipedia.com/wiki/AST-AE084",
        "set_number": "AST-AE084",
        "set_name": "Ancient Sanctuary",
        "rarity": "Rare",
        "date_release": "14 OCTOBER 2004"
    },
    {
        "name": "Order to Charge",
        "passcode": 78986941,
        "konami_id": 6047,
        "wikilink": "https://yugipedia.com/wiki/AST-AE085",
        "set_number": "AST-AE085",
        "set_name": "Ancient Sanctuary",
        "rarity": "Common",
        "date_release": "14 OCTOBER 2004"
    },
    {
        "name": "Sword of the Soul-Eater",
        "passcode": 5371656,
        "konami_id": 6048,
        "wikilink": "https://yugipedia.com/wiki/AST-AE086",
        "set_number": "AST-AE086",
        "set_name": "Ancient Sanctuary",
        "rarity": "Common",
        "date_release": "14 OCTOBER 2004"
    },
    {
        "name": "Dust Barrier",
        "passcode": 31476755,
        "konami_id": 6049,
        "wikilink": "https://yugipedia.com/wiki/AST-AE087",
        "set_number": "AST-AE087",
        "set_name": "Ancient Sanctuary",
        "rarity": "Common",
        "date_release": "14 OCTOBER 2004"
    },
    {
        "name": "Soul Reversal",
        "passcode": 78864369,
        "konami_id": 6050,
        "wikilink": "https://yugipedia.com/wiki/AST-AE088",
        "set_number": "AST-AE088",
        "set_name": "Ancient Sanctuary",
        "rarity": "Common",
        "date_release": "14 OCTOBER 2004"
    },
    {
        "name": "Spell Economics",
        "passcode": 4259068,
        "konami_id": 6051,
        "wikilink": "https://yugipedia.com/wiki/AST-AE089",
        "set_number": "AST-AE089",
        "set_name": "Ancient Sanctuary",
        "rarity": "Rare",
        "date_release": "14 OCTOBER 2004"
    },
    {
        "name": "Blessings of the Nile",
        "passcode": 30653113,
        "konami_id": 6052,
        "wikilink": "https://yugipedia.com/wiki/AST-AE090",
        "set_number": "AST-AE090",
        "set_name": "Ancient Sanctuary",
        "rarity": "Common",
        "date_release": "14 OCTOBER 2004"
    },
    {
        "name": "7",
        "passcode": 67048711,
        "konami_id": 6053,
        "wikilink": "https://yugipedia.com/wiki/AST-AE091",
        "set_number": "AST-AE091",
        "set_name": "Ancient Sanctuary",
        "rarity": "Common",
        "date_release": "14 OCTOBER 2004"
    },
    {
        "name": "Level Limit - Area B",
        "passcode": 3136426,
        "konami_id": 6054,
        "wikilink": "https://yugipedia.com/wiki/AST-AE092",
        "set_number": "AST-AE092",
        "set_name": "Ancient Sanctuary",
        "rarity": "Common",
        "date_release": "14 OCTOBER 2004"
    },
    {
        "name": "Enchanting Fitting Room",
        "passcode": 30531525,
        "konami_id": 6055,
        "wikilink": "https://yugipedia.com/wiki/AST-AE093",
        "set_number": "AST-AE093",
        "set_name": "Ancient Sanctuary",
        "rarity": "Common",
        "date_release": "14 OCTOBER 2004"
    },
    {
        "name": "The Law of the Normal",
        "passcode": 66926224,
        "konami_id": 6056,
        "wikilink": "https://yugipedia.com/wiki/AST-AE094",
        "set_number": "AST-AE094",
        "set_name": "Ancient Sanctuary",
        "rarity": "Common",
        "date_release": "14 OCTOBER 2004"
    },
    {
        "name": "Dark Magic Attack",
        "passcode": 2314238,
        "konami_id": 6057,
        "wikilink": "https://yugipedia.com/wiki/AST-AE095",
        "set_number": "AST-AE095",
        "set_name": "Ancient Sanctuary",
        "rarity": "Ultra Rare",
        "date_release": "14 OCTOBER 2004"
    },
    {
        "name": "Delta Attacker",
        "passcode": 39719977,
        "konami_id": 6058,
        "wikilink": "https://yugipedia.com/wiki/AST-AE096",
        "set_number": "AST-AE096",
        "set_name": "Ancient Sanctuary",
        "rarity": "Common",
        "date_release": "14 OCTOBER 2004"
    },
    {
        "name": "Thousand Energy",
        "passcode": 5703682,
        "konami_id": 6059,
        "wikilink": "https://yugipedia.com/wiki/AST-AE097",
        "set_number": "AST-AE097",
        "set_name": "Ancient Sanctuary",
        "rarity": "Rare",
        "date_release": "14 OCTOBER 2004"
    },
    {
        "name": "Triangle Power",
        "passcode": 32298781,
        "konami_id": 6060,
        "wikilink": "https://yugipedia.com/wiki/AST-AE098",
        "set_number": "AST-AE098",
        "set_name": "Ancient Sanctuary",
        "rarity": "Rare",
        "date_release": "14 OCTOBER 2004"
    },
    {
        "name": "The Third Sarcophagus",
        "passcode": 78697395,
        "konami_id": 6061,
        "wikilink": "https://yugipedia.com/wiki/AST-AE099",
        "set_number": "AST-AE099",
        "set_name": "Ancient Sanctuary",
        "rarity": "Common",
        "date_release": "14 OCTOBER 2004"
    },
    {
        "name": "The Second Sarcophagus",
        "passcode": 4081094,
        "konami_id": 6062,
        "wikilink": "https://yugipedia.com/wiki/AST-AE100",
        "set_number": "AST-AE100",
        "set_name": "Ancient Sanctuary",
        "rarity": "Common",
        "date_release": "14 OCTOBER 2004"
    },
    {
        "name": "The First Sarcophagus",
        "passcode": 31076103,
        "konami_id": 6063,
        "wikilink": "https://yugipedia.com/wiki/AST-AE101",
        "set_number": "AST-AE101",
        "set_name": "Ancient Sanctuary",
        "rarity": "Super Rare",
        "date_release": "14 OCTOBER 2004"
    },
    {
        "name": "Dora of Fate",
        "passcode": 67464807,
        "konami_id": 6064,
        "wikilink": "https://yugipedia.com/wiki/AST-AE102",
        "set_number": "AST-AE102",
        "set_name": "Ancient Sanctuary",
        "rarity": "Common",
        "date_release": "14 OCTOBER 2004"
    },
    {
        "name": "Judgment of the Desert",
        "passcode": 4869446,
        "konami_id": 6065,
        "wikilink": "https://yugipedia.com/wiki/AST-AE103",
        "set_number": "AST-AE103",
        "set_name": "Ancient Sanctuary",
        "rarity": "Common",
        "date_release": "14 OCTOBER 2004"
    },
    {
        "name": "Human-Wave Tactics",
        "passcode": 30353551,
        "konami_id": 6066,
        "wikilink": "https://yugipedia.com/wiki/AST-AE104",
        "set_number": "AST-AE104",
        "set_name": "Ancient Sanctuary",
        "rarity": "Common",
        "date_release": "14 OCTOBER 2004"
    },
    {
        "name": "Curse of Anubis",
        "passcode": 66742250,
        "konami_id": 6067,
        "wikilink": "https://yugipedia.com/wiki/AST-AE105",
        "set_number": "AST-AE105",
        "set_name": "Ancient Sanctuary",
        "rarity": "Ultra Rare",
        "date_release": "14 OCTOBER 2004"
    },
    {
        "name": "Desert Sunlight",
        "passcode": 93747864,
        "konami_id": 6068,
        "wikilink": "https://yugipedia.com/wiki/AST-AE106",
        "set_number": "AST-AE106",
        "set_name": "Ancient Sanctuary",
        "rarity": "Common",
        "date_release": "14 OCTOBER 2004"
    },
    {
        "name": "Des Counterblow",
        "passcode": 39131963,
        "konami_id": 6069,
        "wikilink": "https://yugipedia.com/wiki/AST-AE107",
        "set_number": "AST-AE107",
        "set_name": "Ancient Sanctuary",
        "rarity": "Super Rare",
        "date_release": "14 OCTOBER 2004"
    },
    {
        "name": "Labyrinth of Nightmare",
        "passcode": 66526672,
        "konami_id": 6070,
        "wikilink": "https://yugipedia.com/wiki/AST-AE108",
        "set_number": "AST-AE108",
        "set_name": "Ancient Sanctuary",
        "rarity": "Common",
        "date_release": "14 OCTOBER 2004"
    },
    {
        "name": "Soul Resurrection",
        "passcode": 92924317,
        "konami_id": 6071,
        "wikilink": "https://yugipedia.com/wiki/AST-AE109",
        "set_number": "AST-AE109",
        "set_name": "Ancient Sanctuary",
        "rarity": "Rare",
        "date_release": "14 OCTOBER 2004"
    },
    {
        "name": "Order to Smash",
        "passcode": 39019325,
        "konami_id": 6072,
        "wikilink": "https://yugipedia.com/wiki/AST-AE110",
        "set_number": "AST-AE110",
        "set_name": "Ancient Sanctuary",
        "rarity": "Common",
        "date_release": "14 OCTOBER 2004"
    },
    {
        "name": "Mazera DeVille",
        "passcode": 6133894,
        "konami_id": 5996,
        "wikilink": "https://yugipedia.com/wiki/AST-AE111",
        "set_number": "AST-AE111",
        "set_name": "Ancient Sanctuary",
        "rarity": "Secret Rare",
        "date_release": "14 OCTOBER 2004"
    }
]