[
    {
        "name": "Fallen of Albaz",
        "passcode": 68468459,
        "konami_id": 15245,
        "wikilink": "https://yugipedia.com/wiki/CH01-AE001",
        "set_number": "CH01-AE001",
        "set_name": "THE CHRONICLES DECK: The Fallen & The Virtuous (All-Foil Edition)",
        "rarity": "Normal Parallel Rare",
        "date_release": "25 OCTOBER 2025"
    },
    {
        "name": "Incredible Ecclesia, the Virtuous",
        "passcode": 55273560,
        "konami_id": 16493,
        "wikilink": "https://yugipedia.com/wiki/CH01-AE002",
        "set_number": "CH01-AE002",
        "set_name": "THE CHRONICLES DECK: The Fallen & The Virtuous (All-Foil Edition)",
        "rarity": "Normal Parallel Rare",
        "date_release": "25 OCTOBER 2025"
    },
    {
        "name": "Aluber the Jester of Despia",
        "passcode": 62962630,
        "konami_id": 16195,
        "wikilink": "https://yugipedia.com/wiki/CH01-AE003",
        "set_number": "CH01-AE003",
        "set_name": "THE CHRONICLES DECK: The Fallen & The Virtuous (All-Foil Edition)",
        "rarity": "Normal Parallel Rare",
        "date_release": "25 OCTOBER 2025"
    },
    {
        "name": "Blazing Cartesia, the Virtuous",
        "passcode": 95515789,
        "konami_id": 17767,
        "wikilink": "https://yugipedia.com/wiki/CH01-AE004",
        "set_number": "CH01-AE004",
        "set_name": "THE CHRONICLES DECK: The Fallen & The Virtuous (All-Foil Edition)",
        "rarity": "Normal Parallel Rare",
        "date_release": "25 OCTOBER 2025"
    },
    {
        "name": "Albion the Shrouded Dragon",
        "passcode": 25451383,
        "konami_id": 16197,
        "wikilink": "https://yugipedia.com/wiki/CH01-AE005",
        "set_number": "CH01-AE005",
        "set_name": "THE CHRONICLES DECK: The Fallen & The Virtuous (All-Foil Edition)",
        "rarity": "Common",
        "date_release": "25 OCTOBER 2025"
    },
    {
        "name": "Guiding Quem, the Virtuous",
        "passcode": 45883110,
        "konami_id": 18474,
        "wikilink": "https://yugipedia.com/wiki/CH01-AE006",
        "set_number": "CH01-AE006",
        "set_name": "THE CHRONICLES DECK: The Fallen & The Virtuous (All-Foil Edition)",
        "rarity": "Common",
        "date_release": "25 OCTOBER 2025"
    },
    {
        "name": "Springans Kitt",
        "passcode": 45484331,
        "konami_id": 17063,
        "wikilink": "https://yugipedia.com/wiki/CH01-AE007",
        "set_number": "CH01-AE007",
        "set_name": "THE CHRONICLES DECK: The Fallen & The Virtuous (All-Foil Edition)",
        "rarity": "Common",
        "date_release": "25 OCTOBER 2025"
    },
    {
        "name": "Tri-Brigade Mercourier",
        "passcode": 19096726,
        "konami_id": 17062,
        "wikilink": "https://yugipedia.com/wiki/CH01-AE008",
        "set_number": "CH01-AE008",
        "set_name": "THE CHRONICLES DECK: The Fallen & The Virtuous (All-Foil Edition)",
        "rarity": "Common",
        "date_release": "25 OCTOBER 2025"
    },
    {
        "name": "Despian Tragedy",
        "passcode": 36577931,
        "konami_id": 16194,
        "wikilink": "https://yugipedia.com/wiki/CH01-AE009",
        "set_number": "CH01-AE009",
        "set_name": "THE CHRONICLES DECK: The Fallen & The Virtuous (All-Foil Edition)",
        "rarity": "Common",
        "date_release": "25 OCTOBER 2025"
    },
    {
        "name": "The Bystial Lubellion",
        "passcode": 32731036,
        "konami_id": 17765,
        "wikilink": "https://yugipedia.com/wiki/CH01-AE010",
        "set_number": "CH01-AE010",
        "set_name": "THE CHRONICLES DECK: The Fallen & The Virtuous (All-Foil Edition)",
        "rarity": "Common",
        "date_release": "25 OCTOBER 2025"
    },
    {
        "name": "Bystial Magnamhut",
        "passcode": 33854624,
        "konami_id": 17762,
        "wikilink": "https://yugipedia.com/wiki/CH01-AE011",
        "set_number": "CH01-AE011",
        "set_name": "THE CHRONICLES DECK: The Fallen & The Virtuous (All-Foil Edition)",
        "rarity": "Common",
        "date_release": "25 OCTOBER 2025"
    },
    {
        "name": "Bystial Saronir",
        "passcode": 60242223,
        "konami_id": 17763,
        "wikilink": "https://yugipedia.com/wiki/CH01-AE012",
        "set_number": "CH01-AE012",
        "set_name": "THE CHRONICLES DECK: The Fallen & The Virtuous (All-Foil Edition)",
        "rarity": "Common",
        "date_release": "25 OCTOBER 2025"
    },
    {
        "name": "Bystial Druiswurm",
        "passcode": 6637331,
        "konami_id": 17764,
        "wikilink": "https://yugipedia.com/wiki/CH01-AE013",
        "set_number": "CH01-AE013",
        "set_name": "THE CHRONICLES DECK: The Fallen & The Virtuous (All-Foil Edition)",
        "rarity": "Common",
        "date_release": "25 OCTOBER 2025"
    },
    {
        "name": "Dogmatika Ecclesia, the Virtuous",
        "passcode": 60303688,
        "konami_id": 15239,
        "wikilink": "https://yugipedia.com/wiki/CH01-AE014",
        "set_number": "CH01-AE014",
        "set_name": "THE CHRONICLES DECK: The Fallen & The Virtuous (All-Foil Edition)",
        "rarity": "Super Rare",
        "date_release": "25 OCTOBER 2025"
    },
    {
        "name": "Dogmatika Ecclesia, the Virtuous",
        "passcode": 60303688,
        "konami_id": 15239,
        "wikilink": "https://yugipedia.com/wiki/CH01-AE014",
        "set_number": "CH01-AE014",
        "set_name": "THE CHRONICLES DECK: The Fallen & The Virtuous (All-Foil Edition)",
        "rarity": "",
        "date_release": "25 OCTOBER 2025"
    },
    {
        "name": "Dogmatika Ecclesia, the Virtuous",
        "passcode": 60303688,
        "konami_id": 15239,
        "wikilink": "https://yugipedia.com/wiki/CH01-AE014",
        "set_number": "CH01-AE014",
        "set_name": "THE CHRONICLES DECK: The Fallen & The Virtuous (All-Foil Edition)",
        "rarity": "Secret Rare",
        "date_release": "25 OCTOBER 2025"
    },
    {
        "name": "Dogmatika Fleurdelis, the Knighted",
        "passcode": 69680031,
        "konami_id": 15242,
        "wikilink": "https://yugipedia.com/wiki/CH01-AE015",
        "set_number": "CH01-AE015",
        "set_name": "THE CHRONICLES DECK: The Fallen & The Virtuous (All-Foil Edition)",
        "rarity": "Super Rare",
        "date_release": "25 OCTOBER 2025"
    },
    {
        "name": "Dogmatika Fleurdelis, the Knighted",
        "passcode": 69680031,
        "konami_id": 15242,
        "wikilink": "https://yugipedia.com/wiki/CH01-AE015",
        "set_number": "CH01-AE015",
        "set_name": "THE CHRONICLES DECK: The Fallen & The Virtuous (All-Foil Edition)",
        "rarity": "",
        "date_release": "25 OCTOBER 2025"
    },
    {
        "name": "Dogmatika Fleurdelis, the Knighted",
        "passcode": 69680031,
        "konami_id": 15242,
        "wikilink": "https://yugipedia.com/wiki/CH01-AE015",
        "set_number": "CH01-AE015",
        "set_name": "THE CHRONICLES DECK: The Fallen & The Virtuous (All-Foil Edition)",
        "rarity": "Secret Rare",
        "date_release": "25 OCTOBER 2025"
    },
    {
        "name": "Dogmatika Maximus",
        "passcode": 95679145,
        "konami_id": 15243,
        "wikilink": "https://yugipedia.com/wiki/CH01-AE016",
        "set_number": "CH01-AE016",
        "set_name": "THE CHRONICLES DECK: The Fallen & The Virtuous (All-Foil Edition)",
        "rarity": "Common",
        "date_release": "25 OCTOBER 2025"
    },
    {
        "name": "Nibiru, the Primal Being",
        "passcode": 27204311,
        "konami_id": 14741,
        "wikilink": "https://yugipedia.com/wiki/CH01-AE017",
        "set_number": "CH01-AE017",
        "set_name": "THE CHRONICLES DECK: The Fallen & The Virtuous (All-Foil Edition)",
        "rarity": "Common",
        "date_release": "25 OCTOBER 2025"
    },
    {
        "name": "Keeper of Dragon Magic",
        "passcode": 48048590,
        "konami_id": 13689,
        "wikilink": "https://yugipedia.com/wiki/CH01-AE018",
        "set_number": "CH01-AE018",
        "set_name": "THE CHRONICLES DECK: The Fallen & The Virtuous (All-Foil Edition)",
        "rarity": "Common",
        "date_release": "25 OCTOBER 2025"
    },
    {
        "name": "The Fallen & The Virtuous",
        "passcode": 30271097,
        "konami_id": 22089,
        "wikilink": "https://yugipedia.com/wiki/CH01-AE019",
        "set_number": "CH01-AE019",
        "set_name": "THE CHRONICLES DECK: The Fallen & The Virtuous (All-Foil Edition)",
        "rarity": "Ultra Rare",
        "date_release": "25 OCTOBER 2025"
    },
    {
        "name": "The Fallen & The Virtuous",
        "passcode": 30271097,
        "konami_id": 22089,
        "wikilink": "https://yugipedia.com/wiki/CH01-AE019",
        "set_number": "CH01-AE019",
        "set_name": "THE CHRONICLES DECK: The Fallen & The Virtuous (All-Foil Edition)",
        "rarity": "",
        "date_release": "25 OCTOBER 2025"
    },
    {
        "name": "The Fallen & The Virtuous",
        "passcode": 30271097,
        "konami_id": 22089,
        "wikilink": "https://yugipedia.com/wiki/CH01-AE019",
        "set_number": "CH01-AE019",
        "set_name": "THE CHRONICLES DECK: The Fallen & The Virtuous (All-Foil Edition)",
        "rarity": "Prismatic Secret Rare",
        "date_release": "25 OCTOBER 2025"
    },
    {
        "name": "Branded Fusion",
        "passcode": 44362883,
        "konami_id": 17066,
        "wikilink": "https://yugipedia.com/wiki/CH01-AE020",
        "set_number": "CH01-AE020",
        "set_name": "THE CHRONICLES DECK: The Fallen & The Virtuous (All-Foil Edition)",
        "rarity": "Normal Parallel Rare",
        "date_release": "25 OCTOBER 2025"
    },
    {
        "name": "Branded in White",
        "passcode": 34995106,
        "konami_id": 16016,
        "wikilink": "https://yugipedia.com/wiki/CH01-AE021",
        "set_number": "CH01-AE021",
        "set_name": "THE CHRONICLES DECK: The Fallen & The Virtuous (All-Foil Edition)",
        "rarity": "Common",
        "date_release": "25 OCTOBER 2025"
    },
    {
        "name": "Branded in Red",
        "passcode": 82738008,
        "konami_id": 16543,
        "wikilink": "https://yugipedia.com/wiki/CH01-AE022",
        "set_number": "CH01-AE022",
        "set_name": "THE CHRONICLES DECK: The Fallen & The Virtuous (All-Foil Edition)",
        "rarity": "Common",
        "date_release": "25 OCTOBER 2025"
    },
    {
        "name": "Branded Opening",
        "passcode": 36637374,
        "konami_id": 16243,
        "wikilink": "https://yugipedia.com/wiki/CH01-AE023",
        "set_number": "CH01-AE023",
        "set_name": "THE CHRONICLES DECK: The Fallen & The Virtuous (All-Foil Edition)",
        "rarity": "Common",
        "date_release": "25 OCTOBER 2025"
    },
    {
        "name": "Branded in High Spirits",
        "passcode": 29948294,
        "konami_id": 16541,
        "wikilink": "https://yugipedia.com/wiki/CH01-AE024",
        "set_number": "CH01-AE024",
        "set_name": "THE CHRONICLES DECK: The Fallen & The Virtuous (All-Foil Edition)",
        "rarity": "Normal Parallel Rare",
        "date_release": "25 OCTOBER 2025"
    },
    {
        "name": "Branded Lost",
        "passcode": 18973184,
        "konami_id": 17065,
        "wikilink": "https://yugipedia.com/wiki/CH01-AE025",
        "set_number": "CH01-AE025",
        "set_name": "THE CHRONICLES DECK: The Fallen & The Virtuous (All-Foil Edition)",
        "rarity": "Common",
        "date_release": "25 OCTOBER 2025"
    },
    {
        "name": "Branded Regained",
        "passcode": 34090915,
        "konami_id": 17808,
        "wikilink": "https://yugipedia.com/wiki/CH01-AE026",
        "set_number": "CH01-AE026",
        "set_name": "THE CHRONICLES DECK: The Fallen & The Virtuous (All-Foil Edition)",
        "rarity": "Common",
        "date_release": "25 OCTOBER 2025"
    },
    {
        "name": "Nadir Servant",
        "passcode": 1984618,
        "konami_id": 15286,
        "wikilink": "https://yugipedia.com/wiki/CH01-AE027",
        "set_number": "CH01-AE027",
        "set_name": "THE CHRONICLES DECK: The Fallen & The Virtuous (All-Foil Edition)",
        "rarity": "Common",
        "date_release": "25 OCTOBER 2025"
    },
    {
        "name": "Branded Bond",
        "passcode": 62022479,
        "konami_id": 16244,
        "wikilink": "https://yugipedia.com/wiki/CH01-AE028",
        "set_number": "CH01-AE028",
        "set_name": "THE CHRONICLES DECK: The Fallen & The Virtuous (All-Foil Edition)",
        "rarity": "Common",
        "date_release": "25 OCTOBER 2025"
    },
    {
        "name": "Fusion Deployment",
        "passcode": 6498706,
        "konami_id": 15057,
        "wikilink": "https://yugipedia.com/wiki/CH01-AE029",
        "set_number": "CH01-AE029",
        "set_name": "THE CHRONICLES DECK: The Fallen & The Virtuous (All-Foil Edition)",
        "rarity": "Super Rare",
        "date_release": "25 OCTOBER 2025"
    },
    {
        "name": "Fusion Deployment",
        "passcode": 6498706,
        "konami_id": 15057,
        "wikilink": "https://yugipedia.com/wiki/CH01-AE029",
        "set_number": "CH01-AE029",
        "set_name": "THE CHRONICLES DECK: The Fallen & The Virtuous (All-Foil Edition)",
        "rarity": "",
        "date_release": "25 OCTOBER 2025"
    },
    {
        "name": "Fusion Deployment",
        "passcode": 6498706,
        "konami_id": 15057,
        "wikilink": "https://yugipedia.com/wiki/CH01-AE029",
        "set_number": "CH01-AE029",
        "set_name": "THE CHRONICLES DECK: The Fallen & The Virtuous (All-Foil Edition)",
        "rarity": "Secret Rare",
        "date_release": "25 OCTOBER 2025"
    },
    {
        "name": "Triple Tactics Thrust",
        "passcode": 35269904,
        "konami_id": 18214,
        "wikilink": "https://yugipedia.com/wiki/CH01-AE030",
        "set_number": "CH01-AE030",
        "set_name": "THE CHRONICLES DECK: The Fallen & The Virtuous (All-Foil Edition)",
        "rarity": "Super Rare",
        "date_release": "25 OCTOBER 2025"
    },
    {
        "name": "Triple Tactics Thrust",
        "passcode": 35269904,
        "konami_id": 18214,
        "wikilink": "https://yugipedia.com/wiki/CH01-AE030",
        "set_number": "CH01-AE030",
        "set_name": "THE CHRONICLES DECK: The Fallen & The Virtuous (All-Foil Edition)",
        "rarity": "",
        "date_release": "25 OCTOBER 2025"
    },
    {
        "name": "Triple Tactics Thrust",
        "passcode": 35269904,
        "konami_id": 18214,
        "wikilink": "https://yugipedia.com/wiki/CH01-AE030",
        "set_number": "CH01-AE030",
        "set_name": "THE CHRONICLES DECK: The Fallen & The Virtuous (All-Foil Edition)",
        "rarity": "Secret Rare",
        "date_release": "25 OCTOBER 2025"
    },
    {
        "name": "Foolish Burial",
        "passcode": 0,
        "konami_id": 0,
        "wikilink": "https://yugipedia.com/wiki/CH01-AE031",
        "set_number": "CH01-AE031",
        "set_name": "THE CHRONICLES DECK: The Fallen & The Virtuous (All-Foil Edition)",
        "rarity": "Common",
        "date_release": "25 OCTOBER 2025"
    },
    {
        "name": "Gold Sarcophagus",
        "passcode": 75500286,
        "konami_id": 6161,
        "wikilink": "https://yugipedia.com/wiki/CH01-AE032",
        "set_number": "CH01-AE032",
        "set_name": "THE CHRONICLES DECK: The Fallen & The Virtuous (All-Foil Edition)",
        "rarity": "Common",
        "date_release": "25 OCTOBER 2025"
    },
    {
        "name": "Super Polymerization",
        "passcode": 48130397,
        "konami_id": 7445,
        "wikilink": "https://yugipedia.com/wiki/CH01-AE033",
        "set_number": "CH01-AE033",
        "set_name": "THE CHRONICLES DECK: The Fallen & The Virtuous (All-Foil Edition)",
        "rarity": "Common",
        "date_release": "25 OCTOBER 2025"
    },
    {
        "name": "Branded Retribution",
        "passcode": 17751597,
        "konami_id": 17068,
        "wikilink": "https://yugipedia.com/wiki/CH01-AE034",
        "set_number": "CH01-AE034",
        "set_name": "THE CHRONICLES DECK: The Fallen & The Virtuous (All-Foil Edition)",
        "rarity": "Common",
        "date_release": "25 OCTOBER 2025"
    },
    {
        "name": "Branded Banishment",
        "passcode": 6763530,
        "konami_id": 17183,
        "wikilink": "https://yugipedia.com/wiki/CH01-AE035",
        "set_number": "CH01-AE035",
        "set_name": "THE CHRONICLES DECK: The Fallen & The Virtuous (All-Foil Edition)",
        "rarity": "Common",
        "date_release": "25 OCTOBER 2025"
    },
    {
        "name": "Branded Sword",
        "passcode": 81767888,
        "konami_id": 17067,
        "wikilink": "https://yugipedia.com/wiki/CH01-AE036",
        "set_number": "CH01-AE036",
        "set_name": "THE CHRONICLES DECK: The Fallen & The Virtuous (All-Foil Edition)",
        "rarity": "Common",
        "date_release": "25 OCTOBER 2025"
    },
    {
        "name": "Branded Beast",
        "passcode": 32756828,
        "konami_id": 17828,
        "wikilink": "https://yugipedia.com/wiki/CH01-AE037",
        "set_number": "CH01-AE037",
        "set_name": "THE CHRONICLES DECK: The Fallen & The Virtuous (All-Foil Edition)",
        "rarity": "Common",
        "date_release": "25 OCTOBER 2025"
    },
    {
        "name": "The Black Goat Laughs",
        "passcode": 49299410,
        "konami_id": 19533,
        "wikilink": "https://yugipedia.com/wiki/CH01-AE038",
        "set_number": "CH01-AE038",
        "set_name": "THE CHRONICLES DECK: The Fallen & The Virtuous (All-Foil Edition)",
        "rarity": "Common",
        "date_release": "25 OCTOBER 2025"
    },
    {
        "name": "Dogmatika Punishment",
        "passcode": 82956214,
        "konami_id": 15304,
        "wikilink": "https://yugipedia.com/wiki/CH01-AE039",
        "set_number": "CH01-AE039",
        "set_name": "THE CHRONICLES DECK: The Fallen & The Virtuous (All-Foil Edition)",
        "rarity": "Common",
        "date_release": "25 OCTOBER 2025"
    },
    {
        "name": "Fusion Duplication",
        "passcode": 43331750,
        "konami_id": 18540,
        "wikilink": "https://yugipedia.com/wiki/CH01-AE040",
        "set_number": "CH01-AE040",
        "set_name": "THE CHRONICLES DECK: The Fallen & The Virtuous (All-Foil Edition)",
        "rarity": "Common",
        "date_release": "25 OCTOBER 2025"
    },
    {
        "name": "The Dragon that Devours the Dogma",
        "passcode": 76666602,
        "konami_id": 22090,
        "wikilink": "https://yugipedia.com/wiki/CH01-AE041",
        "set_number": "CH01-AE041",
        "set_name": "THE CHRONICLES DECK: The Fallen & The Virtuous (All-Foil Edition)",
        "rarity": "Ultra Rare",
        "date_release": "25 OCTOBER 2025"
    },
    {
        "name": "The Dragon that Devours the Dogma",
        "passcode": 76666602,
        "konami_id": 22090,
        "wikilink": "https://yugipedia.com/wiki/CH01-AE041",
        "set_number": "CH01-AE041",
        "set_name": "THE CHRONICLES DECK: The Fallen & The Virtuous (All-Foil Edition)",
        "rarity": "",
        "date_release": "25 OCTOBER 2025"
    },
    {
        "name": "The Dragon that Devours the Dogma",
        "passcode": 76666602,
        "konami_id": 22090,
        "wikilink": "https://yugipedia.com/wiki/CH01-AE041",
        "set_number": "CH01-AE041",
        "set_name": "THE CHRONICLES DECK: The Fallen & The Virtuous (All-Foil Edition)",
        "rarity": "Prismatic Secret Rare",
        "date_release": "25 OCTOBER 2025"
    },
    {
        "name": "Mirrorjade the Iceblade Dragon",
        "passcode": 44146295,
        "konami_id": 17069,
        "wikilink": "https://yugipedia.com/wiki/CH01-AE042",
        "set_number": "CH01-AE042",
        "set_name": "THE CHRONICLES DECK: The Fallen & The Virtuous (All-Foil Edition)",
        "rarity": "Normal Parallel Rare",
        "date_release": "25 OCTOBER 2025"
    },
    {
        "name": "Albion the Branded Dragon",
        "passcode": 87746184,
        "konami_id": 15994,
        "wikilink": "https://yugipedia.com/wiki/CH01-AE043",
        "set_number": "CH01-AE043",
        "set_name": "THE CHRONICLES DECK: The Fallen & The Virtuous (All-Foil Edition)",
        "rarity": "Normal Parallel Rare",
        "date_release": "25 OCTOBER 2025"
    },
    {
        "name": "Lubellion the Searing Dragon",
        "passcode": 70534340,
        "konami_id": 17070,
        "wikilink": "https://yugipedia.com/wiki/CH01-AE044",
        "set_number": "CH01-AE044",
        "set_name": "THE CHRONICLES DECK: The Fallen & The Virtuous (All-Foil Edition)",
        "rarity": "Normal Parallel Rare",
        "date_release": "25 OCTOBER 2025"
    },
    {
        "name": "Alba-Lenatus the Abyss Dragon",
        "passcode": 3410461,
        "konami_id": 17146,
        "wikilink": "https://yugipedia.com/wiki/CH01-AE045",
        "set_number": "CH01-AE045",
        "set_name": "THE CHRONICLES DECK: The Fallen & The Virtuous (All-Foil Edition)",
        "rarity": "Common",
        "date_release": "25 OCTOBER 2025"
    },
    {
        "name": "Titaniklad the Ash Dragon",
        "passcode": 41373230,
        "konami_id": 15272,
        "wikilink": "https://yugipedia.com/wiki/CH01-AE046",
        "set_number": "CH01-AE046",
        "set_name": "THE CHRONICLES DECK: The Fallen & The Virtuous (All-Foil Edition)",
        "rarity": "Common",
        "date_release": "25 OCTOBER 2025"
    },
    {
        "name": "Brigrand the Glory Dragon",
        "passcode": 34848821,
        "konami_id": 15510,
        "wikilink": "https://yugipedia.com/wiki/CH01-AE047",
        "set_number": "CH01-AE047",
        "set_name": "THE CHRONICLES DECK: The Fallen & The Virtuous (All-Foil Edition)",
        "rarity": "Common",
        "date_release": "25 OCTOBER 2025"
    },
    {
        "name": "Sprind the Irondash Dragon",
        "passcode": 1906812,
        "konami_id": 15729,
        "wikilink": "https://yugipedia.com/wiki/CH01-AE048",
        "set_number": "CH01-AE048",
        "set_name": "THE CHRONICLES DECK: The Fallen & The Virtuous (All-Foil Edition)",
        "rarity": "Common",
        "date_release": "25 OCTOBER 2025"
    },
    {
        "name": "Rindbrumm the Striking Dragon",
        "passcode": 51409648,
        "konami_id": 18179,
        "wikilink": "https://yugipedia.com/wiki/CH01-AE049",
        "set_number": "CH01-AE049",
        "set_name": "THE CHRONICLES DECK: The Fallen & The Virtuous (All-Foil Edition)",
        "rarity": "Common",
        "date_release": "25 OCTOBER 2025"
    },
    {
        "name": "Granguignol the Dusk Dragon",
        "passcode": 24915933,
        "konami_id": 18178,
        "wikilink": "https://yugipedia.com/wiki/CH01-AE050",
        "set_number": "CH01-AE050",
        "set_name": "THE CHRONICLES DECK: The Fallen & The Virtuous (All-Foil Edition)",
        "rarity": "Normal Parallel Rare",
        "date_release": "25 OCTOBER 2025"
    }
]