[
    {
        "name": "Salamangreat Pyro Phoenix",
        "passcode": 31313405,
        "konami_id": 14666,
        "wikilink": "https://yugipedia.com/wiki/SDSS-AEP01",
        "set_number": "SDSS-AEP01",
        "set_name": "Structure Deck: Salamangreat Sanctum Transcend Power-Up Pack",
        "rarity": "Secret Rare",
        "date_release": "18 MAY 2024"
    },
    {
        "name": "Salamangreat Raging Phoenix",
        "passcode": 57134592,
        "konami_id": 18912,
        "wikilink": "https://yugipedia.com/wiki/SDSS-AEP02",
        "set_number": "SDSS-AEP02",
        "set_name": "Structure Deck: Salamangreat Sanctum Transcend Power-Up Pack",
        "rarity": "Secret Rare",
        "date_release": "18 MAY 2024"
    },
    {
        "name": "Salamangreat Violet Chimera",
        "passcode": 37261776,
        "konami_id": 14111,
        "wikilink": "https://yugipedia.com/wiki/SDSS-AEP03",
        "set_number": "SDSS-AEP03",
        "set_name": "Structure Deck: Salamangreat Sanctum Transcend Power-Up Pack",
        "rarity": "Ultra Rare",
        "date_release": "18 MAY 2024"
    },
    {
        "name": "Salamangreat Burst Gryphon",
        "passcode": 10140443,
        "konami_id": 18911,
        "wikilink": "https://yugipedia.com/wiki/SDSS-AEP04",
        "set_number": "SDSS-AEP04",
        "set_name": "Structure Deck: Salamangreat Sanctum Transcend Power-Up Pack",
        "rarity": "Ultra Rare",
        "date_release": "18 MAY 2024"
    },
    {
        "name": "Salamangreat Heatleo",
        "passcode": 41463181,
        "konami_id": 13927,
        "wikilink": "https://yugipedia.com/wiki/SDSS-AEP05",
        "set_number": "SDSS-AEP05",
        "set_name": "Structure Deck: Salamangreat Sanctum Transcend Power-Up Pack",
        "rarity": "Ultra Rare",
        "date_release": "18 MAY 2024"
    },
    {
        "name": "Salamangreat Sunlight Wolf",
        "passcode": 87871125,
        "konami_id": 14125,
        "wikilink": "https://yugipedia.com/wiki/SDSS-AEP06",
        "set_number": "SDSS-AEP06",
        "set_name": "Structure Deck: Salamangreat Sanctum Transcend Power-Up Pack",
        "rarity": "Ultra Rare",
        "date_release": "18 MAY 2024"
    },
    {
        "name": "Dogoran, the Mad Flame Kaiju",
        "passcode": 93332803,
        "konami_id": 12038,
        "wikilink": "https://yugipedia.com/wiki/SDSS-AEP07",
        "set_number": "SDSS-AEP07",
        "set_name": "Structure Deck: Salamangreat Sanctum Transcend Power-Up Pack",
        "rarity": "Super Rare",
        "date_release": "18 MAY 2024"
    },
    {
        "name": "Salamangreat Almiraj",
        "passcode": 60303245,
        "konami_id": 14338,
        "wikilink": "https://yugipedia.com/wiki/SDSS-AEP08",
        "set_number": "SDSS-AEP08",
        "set_name": "Structure Deck: Salamangreat Sanctum Transcend Power-Up Pack",
        "rarity": "Super Rare",
        "date_release": "18 MAY 2024"
    },
    {
        "name": "Knightmare Phoenix",
        "passcode": 2857636,
        "konami_id": 13600,
        "wikilink": "https://yugipedia.com/wiki/SDSS-AEP09",
        "set_number": "SDSS-AEP09",
        "set_name": "Structure Deck: Salamangreat Sanctum Transcend Power-Up Pack",
        "rarity": "Super Rare",
        "date_release": "18 MAY 2024"
    },
    {
        "name": "Kaiser Colosseum",
        "passcode": 35059553,
        "konami_id": 5605,
        "wikilink": "https://yugipedia.com/wiki/SDSS-AEP10",
        "set_number": "SDSS-AEP10",
        "set_name": "Structure Deck: Salamangreat Sanctum Transcend Power-Up Pack",
        "rarity": "Super Rare",
        "date_release": "18 MAY 2024"
    },
    {
        "name": "Triple Tactics Thrust",
        "passcode": 35269904,
        "konami_id": 18214,
        "wikilink": "https://yugipedia.com/wiki/SDSS-AEP11",
        "set_number": "SDSS-AEP11",
        "set_name": "Structure Deck: Salamangreat Sanctum Transcend Power-Up Pack",
        "rarity": "Super Rare",
        "date_release": "18 MAY 2024"
    },
    {
        "name": "Red Reboot",
        "passcode": 23002292,
        "konami_id": 13622,
        "wikilink": "https://yugipedia.com/wiki/SDSS-AEP12",
        "set_number": "SDSS-AEP12",
        "set_name": "Structure Deck: Salamangreat Sanctum Transcend Power-Up Pack",
        "rarity": "Super Rare",
        "date_release": "18 MAY 2024"
    }
]