[
    {
        "name": "Exosister Martha",
        "passcode": 37343995,
        "wikilink": "https://yugipedia.com/wiki/TT02-AEB01",
        "set_number": "TT02-AEB01",
        "rarity": "Common",
        "date_release": "24 MAY 2025"
    },
    {
        "name": "Exosister Elis",
        "passcode": 16474916,
        "wikilink": "https://yugipedia.com/wiki/TT02-AEB02",
        "set_number": "TT02-AEB02",
        "rarity": "Common",
        "date_release": "24 MAY 2025"
    },
    {
        "name": "Exosister Stella",
        "passcode": 43863925,
        "wikilink": "https://yugipedia.com/wiki/TT02-AEB03",
        "set_number": "TT02-AEB03",
        "rarity": "Common",
        "date_release": "24 MAY 2025"
    },
    {
        "name": "Exosister Irene",
        "passcode": 79858629,
        "wikilink": "https://yugipedia.com/wiki/TT02-AEB04",
        "set_number": "TT02-AEB04",
        "rarity": "Common",
        "date_release": "24 MAY 2025"
    },
    {
        "name": "Exosister Sophia",
        "passcode": 5352328,
        "wikilink": "https://yugipedia.com/wiki/TT02-AEB05",
        "set_number": "TT02-AEB05",
        "rarity": "Common",
        "date_release": "24 MAY 2025"
    },
    {
        "name": "Aratama",
        "passcode": 16889337,
        "wikilink": "https://yugipedia.com/wiki/TT02-AEB06",
        "set_number": "TT02-AEB06",
        "rarity": "Common",
        "date_release": "24 MAY 2025"
    },
    {
        "name": "Sakitama",
        "passcode": 67972302,
        "wikilink": "https://yugipedia.com/wiki/TT02-AEB07",
        "set_number": "TT02-AEB07",
        "rarity": "Common",
        "date_release": "24 MAY 2025"
    },
    {
        "name": "Nibiru, the Primal Being",
        "passcode": 27204311,
        "wikilink": "https://yugipedia.com/wiki/TT02-AEB08",
        "set_number": "TT02-AEB08",
        "rarity": "Common",
        "date_release": "24 MAY 2025"
    },
    {
        "name": "Dimension Shifter",
        "passcode": 91800273,
        "wikilink": "https://yugipedia.com/wiki/TT02-AEB09",
        "set_number": "TT02-AEB09",
        "rarity": "Common",
        "date_release": "24 MAY 2025"
    },
    {
        "name": "Ghost Ogre & Snow Rabbit",
        "passcode": 59438930,
        "wikilink": "https://yugipedia.com/wiki/TT02-AEB10",
        "set_number": "TT02-AEB10",
        "rarity": "Common",
        "date_release": "24 MAY 2025"
    },
    {
        "name": "Ash Blossom & Joyous Spring",
        "passcode": 14558127,
        "wikilink": "https://yugipedia.com/wiki/TT02-AEB11",
        "set_number": "TT02-AEB11",
        "rarity": "Common",
        "date_release": "24 MAY 2025"
    },
    {
        "name": "Maxx \"C\"",
        "passcode": 23434538,
        "wikilink": "https://yugipedia.com/wiki/TT02-AEB12",
        "set_number": "TT02-AEB12",
        "rarity": "Common",
        "date_release": "24 MAY 2025"
    },
    {
        "name": "Exosister Pax",
        "passcode": 77913594,
        "wikilink": "https://yugipedia.com/wiki/TT02-AEB13",
        "set_number": "TT02-AEB13",
        "rarity": "Common",
        "date_release": "24 MAY 2025"
    },
    {
        "name": "Exosister Arment",
        "passcode": 4408198,
        "wikilink": "https://yugipedia.com/wiki/TT02-AEB14",
        "set_number": "TT02-AEB14",
        "rarity": "Common",
        "date_release": "24 MAY 2025"
    },
    {
        "name": "Exosister Carpedivem",
        "passcode": 30802207,
        "wikilink": "https://yugipedia.com/wiki/TT02-AEB15",
        "set_number": "TT02-AEB15",
        "rarity": "Common",
        "date_release": "24 MAY 2025"
    },
    {
        "name": "Triple Tactics Talent",
        "passcode": 25311006,
        "wikilink": "https://yugipedia.com/wiki/TT02-AEB16",
        "set_number": "TT02-AEB16",
        "rarity": "Common",
        "date_release": "24 MAY 2025"
    },
    {
        "name": "Called by the Grave",
        "passcode": 24224830,
        "wikilink": "https://yugipedia.com/wiki/TT02-AEB17",
        "set_number": "TT02-AEB17",
        "rarity": "Common",
        "date_release": "24 MAY 2025"
    },
    {
        "name": "Crossout Designator",
        "passcode": 65681983,
        "wikilink": "https://yugipedia.com/wiki/TT02-AEB18",
        "set_number": "TT02-AEB18",
        "rarity": "Common",
        "date_release": "24 MAY 2025"
    },
    {
        "name": "Exosister Vadis",
        "passcode": 77891946,
        "wikilink": "https://yugipedia.com/wiki/TT02-AEB19",
        "set_number": "TT02-AEB19",
        "rarity": "Common",
        "date_release": "24 MAY 2025"
    },
    {
        "name": "Exosister Returnia",
        "passcode": 197042,
        "wikilink": "https://yugipedia.com/wiki/TT02-AEB20",
        "set_number": "TT02-AEB20",
        "rarity": "Common",
        "date_release": "24 MAY 2025"
    },
    {
        "name": "Solemn Judgment",
        "passcode": 41420027,
        "wikilink": "https://yugipedia.com/wiki/TT02-AEB21",
        "set_number": "TT02-AEB21",
        "rarity": "Common",
        "date_release": "24 MAY 2025"
    },
    {
        "name": "Infinite Impermanence",
        "passcode": 10045474,
        "wikilink": "https://yugipedia.com/wiki/TT02-AEB22",
        "set_number": "TT02-AEB22",
        "rarity": "Common",
        "date_release": "24 MAY 2025"
    },
    {
        "name": "Exosisters Magnifica",
        "passcode": 59242457,
        "wikilink": "https://yugipedia.com/wiki/TT02-AEB23",
        "set_number": "TT02-AEB23",
        "rarity": "Common",
        "date_release": "24 MAY 2025"
    },
    {
        "name": "Exosisters Magnifica",
        "passcode": 59242457,
        "wikilink": "https://yugipedia.com/wiki/TT02-AEB23",
        "set_number": "TT02-AEB23",
        "rarity": "",
        "date_release": "24 MAY 2025"
    },
    {
        "name": "Exosisters Magnifica",
        "passcode": 59242457,
        "wikilink": "https://yugipedia.com/wiki/TT02-AEB23",
        "set_number": "TT02-AEB23",
        "rarity": "Ultra Rare",
        "date_release": "24 MAY 2025"
    },
    {
        "name": "Exosister Mikailis",
        "passcode": 42741437,
        "wikilink": "https://yugipedia.com/wiki/TT02-AEB24",
        "set_number": "TT02-AEB24",
        "rarity": "Common",
        "date_release": "24 MAY 2025"
    },
    {
        "name": "Exosister Kaspitell",
        "passcode": 78135071,
        "wikilink": "https://yugipedia.com/wiki/TT02-AEB25",
        "set_number": "TT02-AEB25",
        "rarity": "Common",
        "date_release": "24 MAY 2025"
    },
    {
        "name": "Exosister Gibrine",
        "passcode": 5530780,
        "wikilink": "https://yugipedia.com/wiki/TT02-AEB26",
        "set_number": "TT02-AEB26",
        "rarity": "Common",
        "date_release": "24 MAY 2025"
    },
    {
        "name": "Exosister Asophiel",
        "passcode": 41524885,
        "wikilink": "https://yugipedia.com/wiki/TT02-AEB27",
        "set_number": "TT02-AEB27",
        "rarity": "Common",
        "date_release": "24 MAY 2025"
    },
    {
        "name": "Divine Arsenal AA-ZEUS - Sky Thunder",
        "passcode": 90448279,
        "wikilink": "https://yugipedia.com/wiki/TT02-AEB28",
        "set_number": "TT02-AEB28",
        "rarity": "Common",
        "date_release": "24 MAY 2025"
    }
]