[
    {
        "name": "Blue-Eyes Toon Dragon",
        "passcode": 53183600,
        "wikilink": "https://yugipedia.com/wiki/MRL-000",
        "set_number": "MRL-000",
        "rarity": "Secret Rare",
        "date_release": "24 October 2002"
    },
    {
        "name": "Penguin Knight",
        "passcode": 36039163,
        "wikilink": "https://yugipedia.com/wiki/MRL-001",
        "set_number": "MRL-001",
        "rarity": "Common",
        "date_release": "24 October 2002"
    },
    {
        "name": "Axe of Despair",
        "passcode": 40619825,
        "wikilink": "https://yugipedia.com/wiki/MRL-002",
        "set_number": "MRL-002",
        "rarity": "Ultra Rare",
        "date_release": "24 October 2002"
    },
    {
        "name": "Black Pendant",
        "passcode": 65169794,
        "wikilink": "https://yugipedia.com/wiki/MRL-003",
        "set_number": "MRL-003",
        "rarity": "Super Rare",
        "date_release": "24 October 2002"
    },
    {
        "name": "Horn of Light",
        "passcode": 38552107,
        "wikilink": "https://yugipedia.com/wiki/MRL-004",
        "set_number": "MRL-004",
        "rarity": "Common",
        "date_release": "24 October 2002"
    },
    {
        "name": "Malevolent Nuzzler",
        "passcode": 99597615,
        "wikilink": "https://yugipedia.com/wiki/MRL-005",
        "set_number": "MRL-005",
        "rarity": "Common",
        "date_release": "24 October 2002"
    },
    {
        "name": "Spellbinding Circle",
        "passcode": 18807108,
        "wikilink": "https://yugipedia.com/wiki/MRL-006",
        "set_number": "MRL-006",
        "rarity": "Ultra Rare",
        "date_release": "24 October 2002"
    },
    {
        "name": "Metal Fish",
        "passcode": 55998462,
        "wikilink": "https://yugipedia.com/wiki/MRL-007",
        "set_number": "MRL-007",
        "rarity": "Common",
        "date_release": "24 October 2002"
    },
    {
        "name": "Electric Snake",
        "passcode": 11324436,
        "wikilink": "https://yugipedia.com/wiki/MRL-008",
        "set_number": "MRL-008",
        "rarity": "Common",
        "date_release": "24 October 2002"
    },
    {
        "name": "Queen Bird",
        "passcode": 73081602,
        "wikilink": "https://yugipedia.com/wiki/MRL-009",
        "set_number": "MRL-009",
        "rarity": "Common",
        "date_release": "24 October 2002"
    },
    {
        "name": "Ameba",
        "passcode": 95174353,
        "wikilink": "https://yugipedia.com/wiki/MRL-010",
        "set_number": "MRL-010",
        "rarity": "Rare",
        "date_release": "24 October 2002"
    },
    {
        "name": "Peacock",
        "passcode": 20624263,
        "wikilink": "https://yugipedia.com/wiki/MRL-011",
        "set_number": "MRL-011",
        "rarity": "Common",
        "date_release": "24 October 2002"
    },
    {
        "name": "Maha Vailo",
        "passcode": 93013676,
        "wikilink": "https://yugipedia.com/wiki/MRL-012",
        "set_number": "MRL-012",
        "rarity": "Super Rare",
        "date_release": "24 October 2002"
    },
    {
        "name": "Guardian of the Throne Room",
        "passcode": 47879985,
        "wikilink": "https://yugipedia.com/wiki/MRL-013",
        "set_number": "MRL-013",
        "rarity": "Common",
        "date_release": "24 October 2002"
    },
    {
        "name": "Fire Kraken",
        "passcode": 46534755,
        "wikilink": "https://yugipedia.com/wiki/MRL-014",
        "set_number": "MRL-014",
        "rarity": "Common",
        "date_release": "24 October 2002"
    },
    {
        "name": "Minar",
        "passcode": 32539892,
        "wikilink": "https://yugipedia.com/wiki/MRL-015",
        "set_number": "MRL-015",
        "rarity": "Common",
        "date_release": "24 October 2002"
    },
    {
        "name": "Griggle",
        "passcode": 95744531,
        "wikilink": "https://yugipedia.com/wiki/MRL-016",
        "set_number": "MRL-016",
        "rarity": "Common",
        "date_release": "24 October 2002"
    },
    {
        "name": "Tyhone 2",
        "passcode": 56789759,
        "wikilink": "https://yugipedia.com/wiki/MRL-017",
        "set_number": "MRL-017",
        "rarity": "Common",
        "date_release": "24 October 2002"
    },
    {
        "name": "Ancient One of the Deep Forest",
        "passcode": 14015067,
        "wikilink": "https://yugipedia.com/wiki/MRL-018",
        "set_number": "MRL-018",
        "rarity": "Common",
        "date_release": "24 October 2002"
    },
    {
        "name": "Dark Witch",
        "passcode": 35565537,
        "wikilink": "https://yugipedia.com/wiki/MRL-019",
        "set_number": "MRL-019",
        "rarity": "Common",
        "date_release": "24 October 2002"
    },
    {
        "name": "Weather Report",
        "passcode": 72053645,
        "wikilink": "https://yugipedia.com/wiki/MRL-020",
        "set_number": "MRL-020",
        "rarity": "Common",
        "date_release": "24 October 2002"
    },
    {
        "name": "Mechanical Snail",
        "passcode": 34442949,
        "wikilink": "https://yugipedia.com/wiki/MRL-021",
        "set_number": "MRL-021",
        "rarity": "Common",
        "date_release": "24 October 2002"
    },
    {
        "name": "Giant Turtle Who Feeds on Flames",
        "passcode": 96981563,
        "wikilink": "https://yugipedia.com/wiki/MRL-022",
        "set_number": "MRL-022",
        "rarity": "Common",
        "date_release": "24 October 2002"
    },
    {
        "name": "Liquid Beast",
        "passcode": 93108297,
        "wikilink": "https://yugipedia.com/wiki/MRL-023",
        "set_number": "MRL-023",
        "rarity": "Common",
        "date_release": "24 October 2002"
    },
    {
        "name": "Hiro's Shadow Scout",
        "passcode": 81863068,
        "wikilink": "https://yugipedia.com/wiki/MRL-024",
        "set_number": "MRL-024",
        "rarity": "Rare",
        "date_release": "24 October 2002"
    },
    {
        "name": "High Tide Gyojin",
        "passcode": 54579801,
        "wikilink": "https://yugipedia.com/wiki/MRL-025",
        "set_number": "MRL-025",
        "rarity": "Common",
        "date_release": "24 October 2002"
    },
    {
        "name": "Invader of the Throne",
        "passcode": 3056267,
        "wikilink": "https://yugipedia.com/wiki/MRL-026",
        "set_number": "MRL-026",
        "rarity": "Super Rare",
        "date_release": "24 October 2002"
    },
    {
        "name": "Whiptail Crow",
        "passcode": 91996584,
        "wikilink": "https://yugipedia.com/wiki/MRL-027",
        "set_number": "MRL-027",
        "rarity": "Common",
        "date_release": "24 October 2002"
    },
    {
        "name": "Slot Machine",
        "passcode": 3797883,
        "wikilink": "https://yugipedia.com/wiki/MRL-028",
        "set_number": "MRL-028",
        "rarity": "Normal Rare",
        "date_release": "24 October 2002"
    },
    {
        "name": "Relinquished",
        "passcode": 64631466,
        "wikilink": "https://yugipedia.com/wiki/MRL-029",
        "set_number": "MRL-029",
        "rarity": "Ultra Rare",
        "date_release": "24 October 2002"
    },
    {
        "name": "Red Archery Girl",
        "passcode": 65570596,
        "wikilink": "https://yugipedia.com/wiki/MRL-030",
        "set_number": "MRL-030",
        "rarity": "Common",
        "date_release": "24 October 2002"
    },
    {
        "name": "Gravekeeper's Servant",
        "passcode": 16762927,
        "wikilink": "https://yugipedia.com/wiki/MRL-031",
        "set_number": "MRL-031",
        "rarity": "Normal Rare",
        "date_release": "24 October 2002"
    },
    {
        "name": "Curse of Fiend",
        "passcode": 12470447,
        "wikilink": "https://yugipedia.com/wiki/MRL-032",
        "set_number": "MRL-032",
        "rarity": "Normal Rare",
        "date_release": "24 October 2002"
    },
    {
        "name": "Upstart Goblin",
        "passcode": 70368879,
        "wikilink": "https://yugipedia.com/wiki/MRL-033",
        "set_number": "MRL-033",
        "rarity": "Common",
        "date_release": "24 October 2002"
    },
    {
        "name": "Toll",
        "passcode": 82003859,
        "wikilink": "https://yugipedia.com/wiki/MRL-034",
        "set_number": "MRL-034",
        "rarity": "Normal Rare",
        "date_release": "24 October 2002"
    },
    {
        "name": "Final Destiny",
        "passcode": 18591904,
        "wikilink": "https://yugipedia.com/wiki/MRL-035",
        "set_number": "MRL-035",
        "rarity": "Common",
        "date_release": "24 October 2002"
    },
    {
        "name": "Snatch Steal",
        "passcode": 45986603,
        "wikilink": "https://yugipedia.com/wiki/MRL-036",
        "set_number": "MRL-036",
        "rarity": "Ultra Rare",
        "date_release": "24 October 2002"
    },
    {
        "name": "Chorus of Sanctuary",
        "passcode": 81380218,
        "wikilink": "https://yugipedia.com/wiki/MRL-037",
        "set_number": "MRL-037",
        "rarity": "Common",
        "date_release": "24 October 2002"
    },
    {
        "name": "Confiscation",
        "passcode": 17375316,
        "wikilink": "https://yugipedia.com/wiki/MRL-038",
        "set_number": "MRL-038",
        "rarity": "Super Rare",
        "date_release": "24 October 2002"
    },
    {
        "name": "Delinquent Duo",
        "passcode": 44763025,
        "wikilink": "https://yugipedia.com/wiki/MRL-039",
        "set_number": "MRL-039",
        "rarity": "Ultra Rare",
        "date_release": "24 October 2002"
    },
    {
        "name": "Darkness Approaches",
        "passcode": 80168720,
        "wikilink": "https://yugipedia.com/wiki/MRL-040",
        "set_number": "MRL-040",
        "rarity": "Normal Rare",
        "date_release": "24 October 2002"
    },
    {
        "name": "Fairy's Hand Mirror",
        "passcode": 17653779,
        "wikilink": "https://yugipedia.com/wiki/MRL-041",
        "set_number": "MRL-041",
        "rarity": "Normal Rare",
        "date_release": "24 October 2002"
    },
    {
        "name": "Tailor of the Fickle",
        "passcode": 43641473,
        "wikilink": "https://yugipedia.com/wiki/MRL-042",
        "set_number": "MRL-042",
        "rarity": "Normal Rare",
        "date_release": "24 October 2002"
    },
    {
        "name": "Rush Recklessly",
        "passcode": 70046172,
        "wikilink": "https://yugipedia.com/wiki/MRL-043",
        "set_number": "MRL-043",
        "rarity": "Rare",
        "date_release": "24 October 2002"
    },
    {
        "name": "The Reliable Guardian",
        "passcode": 16430187,
        "wikilink": "https://yugipedia.com/wiki/MRL-044",
        "set_number": "MRL-044",
        "rarity": "Common",
        "date_release": "24 October 2002"
    },
    {
        "name": "The Forceful Sentry",
        "passcode": 42829885,
        "wikilink": "https://yugipedia.com/wiki/MRL-045",
        "set_number": "MRL-045",
        "rarity": "Ultra Rare",
        "date_release": "24 October 2002"
    },
    {
        "name": "Chain Energy",
        "passcode": 79323590,
        "wikilink": "https://yugipedia.com/wiki/MRL-046",
        "set_number": "MRL-046",
        "rarity": "Common",
        "date_release": "24 October 2002"
    },
    {
        "name": "Mystical Space Typhoon",
        "passcode": 5318639,
        "wikilink": "https://yugipedia.com/wiki/MRL-047",
        "set_number": "MRL-047",
        "rarity": "Ultra Rare",
        "date_release": "24 October 2002"
    },
    {
        "name": "Giant Trunade",
        "passcode": 42703248,
        "wikilink": "https://yugipedia.com/wiki/MRL-048",
        "set_number": "MRL-048",
        "rarity": "Super Rare",
        "date_release": "24 October 2002"
    },
    {
        "name": "Painful Choice",
        "passcode": 74191942,
        "wikilink": "https://yugipedia.com/wiki/MRL-049",
        "set_number": "MRL-049",
        "rarity": "Super Rare",
        "date_release": "24 October 2002"
    },
    {
        "name": "Snake Fang",
        "passcode": 596051,
        "wikilink": "https://yugipedia.com/wiki/MRL-050",
        "set_number": "MRL-050",
        "rarity": "Common",
        "date_release": "24 October 2002"
    },
    {
        "name": "Black Illusion Ritual",
        "passcode": 41426869,
        "wikilink": "https://yugipedia.com/wiki/MRL-051",
        "set_number": "MRL-051",
        "rarity": "Super Rare",
        "date_release": "24 October 2002"
    },
    {
        "name": "Octoberser",
        "passcode": 74637266,
        "wikilink": "https://yugipedia.com/wiki/MRL-052",
        "set_number": "MRL-052",
        "rarity": "Common",
        "date_release": "24 October 2002"
    },
    {
        "name": "Psychic Kappa",
        "passcode": 7892180,
        "wikilink": "https://yugipedia.com/wiki/MRL-053",
        "set_number": "MRL-053",
        "rarity": "Common",
        "date_release": "24 October 2002"
    },
    {
        "name": "Horn of the Unicorn",
        "passcode": 64047146,
        "wikilink": "https://yugipedia.com/wiki/MRL-054",
        "set_number": "MRL-054",
        "rarity": "Rare",
        "date_release": "24 October 2002"
    },
    {
        "name": "Labyrinth Wall",
        "passcode": 67284908,
        "wikilink": "https://yugipedia.com/wiki/MRL-055",
        "set_number": "MRL-055",
        "rarity": "Common",
        "date_release": "24 October 2002"
    },
    {
        "name": "Wall Shadow",
        "passcode": 63162310,
        "wikilink": "https://yugipedia.com/wiki/MRL-056",
        "set_number": "MRL-056",
        "rarity": "Common",
        "date_release": "24 October 2002"
    },
    {
        "name": "Twin Long Rods 2",
        "passcode": 29692206,
        "wikilink": "https://yugipedia.com/wiki/MRL-057",
        "set_number": "MRL-057",
        "rarity": "Common",
        "date_release": "24 October 2002"
    },
    {
        "name": "Stone Ogre Grotto",
        "passcode": 15023985,
        "wikilink": "https://yugipedia.com/wiki/MRL-058",
        "set_number": "MRL-058",
        "rarity": "Common",
        "date_release": "24 October 2002"
    },
    {
        "name": "Magical Labyrinth",
        "passcode": 64389297,
        "wikilink": "https://yugipedia.com/wiki/MRL-059",
        "set_number": "MRL-059",
        "rarity": "Common",
        "date_release": "24 October 2002"
    },
    {
        "name": "Eternal Rest",
        "passcode": 95051344,
        "wikilink": "https://yugipedia.com/wiki/MRL-060",
        "set_number": "MRL-060",
        "rarity": "Normal Rare",
        "date_release": "24 October 2002"
    },
    {
        "name": "Megamorph",
        "passcode": 22046459,
        "wikilink": "https://yugipedia.com/wiki/MRL-061",
        "set_number": "MRL-061",
        "rarity": "Ultra Rare",
        "date_release": "24 October 2002"
    },
    {
        "name": "Commencement Dance",
        "passcode": 43417563,
        "wikilink": "https://yugipedia.com/wiki/MRL-062",
        "set_number": "MRL-062",
        "rarity": "Common",
        "date_release": "24 October 2002"
    },
    {
        "name": "Hamburger Recipe",
        "passcode": 80811661,
        "wikilink": "https://yugipedia.com/wiki/MRL-063",
        "set_number": "MRL-063",
        "rarity": "Common",
        "date_release": "24 October 2002"
    },
    {
        "name": "House of Adhesive Tape",
        "passcode": 15083728,
        "wikilink": "https://yugipedia.com/wiki/MRL-064",
        "set_number": "MRL-064",
        "rarity": "Common",
        "date_release": "24 October 2002"
    },
    {
        "name": "Eatgaboon",
        "passcode": 42578427,
        "wikilink": "https://yugipedia.com/wiki/MRL-065",
        "set_number": "MRL-065",
        "rarity": "Common",
        "date_release": "24 October 2002"
    },
    {
        "name": "Turtle Oath",
        "passcode": 76806714,
        "wikilink": "https://yugipedia.com/wiki/MRL-066",
        "set_number": "MRL-066",
        "rarity": "Common",
        "date_release": "24 October 2002"
    },
    {
        "name": "Performance of Sword",
        "passcode": 4849037,
        "wikilink": "https://yugipedia.com/wiki/MRL-067",
        "set_number": "MRL-067",
        "rarity": "Common",
        "date_release": "24 October 2002"
    },
    {
        "name": "Hungry Burger",
        "passcode": 30243636,
        "wikilink": "https://yugipedia.com/wiki/MRL-068",
        "set_number": "MRL-068",
        "rarity": "Common",
        "date_release": "24 October 2002"
    },
    {
        "name": "Crab Turtle",
        "passcode": 91782219,
        "wikilink": "https://yugipedia.com/wiki/MRL-069",
        "set_number": "MRL-069",
        "rarity": "Common",
        "date_release": "24 October 2002"
    },
    {
        "name": "Ryu-Ran",
        "passcode": 2964201,
        "wikilink": "https://yugipedia.com/wiki/MRL-070",
        "set_number": "MRL-070",
        "rarity": "Common",
        "date_release": "24 October 2002"
    },
    {
        "name": "Manga Ryu-Ran",
        "passcode": 38369349,
        "wikilink": "https://yugipedia.com/wiki/MRL-071",
        "set_number": "MRL-071",
        "rarity": "Rare",
        "date_release": "24 October 2002"
    },
    {
        "name": "Toon Mermaid",
        "passcode": 65458948,
        "wikilink": "https://yugipedia.com/wiki/MRL-072",
        "set_number": "MRL-072",
        "rarity": "Ultra Rare",
        "date_release": "24 October 2002"
    },
    {
        "name": "Toon Summoned Skull",
        "passcode": 91842653,
        "wikilink": "https://yugipedia.com/wiki/MRL-073",
        "set_number": "MRL-073",
        "rarity": "Ultra Rare",
        "date_release": "24 October 2002"
    },
    {
        "name": "Jigen Bakudan",
        "passcode": 90020065,
        "wikilink": "https://yugipedia.com/wiki/MRL-074",
        "set_number": "MRL-074",
        "rarity": "Normal Rare",
        "date_release": "24 October 2002"
    },
    {
        "name": "Hyozanryu",
        "passcode": 62397231,
        "wikilink": "https://yugipedia.com/wiki/MRL-075",
        "set_number": "MRL-075",
        "rarity": "Rare",
        "date_release": "24 October 2002"
    },
    {
        "name": "Toon World",
        "passcode": 15259703,
        "wikilink": "https://yugipedia.com/wiki/MRL-076",
        "set_number": "MRL-076",
        "rarity": "Super Rare",
        "date_release": "24 October 2002"
    },
    {
        "name": "Cyber Jar",
        "passcode": 34124316,
        "wikilink": "https://yugipedia.com/wiki/MRL-077",
        "set_number": "MRL-077",
        "rarity": "Rare",
        "date_release": "24 October 2002"
    },
    {
        "name": "Banisher of the Light",
        "passcode": 61528025,
        "wikilink": "https://yugipedia.com/wiki/MRL-078",
        "set_number": "MRL-078",
        "rarity": "Super Rare",
        "date_release": "24 October 2002"
    },
    {
        "name": "Giant Rat",
        "passcode": 97017120,
        "wikilink": "https://yugipedia.com/wiki/MRL-079",
        "set_number": "MRL-079",
        "rarity": "Rare",
        "date_release": "24 October 2002"
    },
    {
        "name": "Senju of the Thousand Hands",
        "passcode": 23401839,
        "wikilink": "https://yugipedia.com/wiki/MRL-080",
        "set_number": "MRL-080",
        "rarity": "Rare",
        "date_release": "24 October 2002"
    },
    {
        "name": "UFO Turtle",
        "passcode": 60806437,
        "wikilink": "https://yugipedia.com/wiki/MRL-081",
        "set_number": "MRL-081",
        "rarity": "Rare",
        "date_release": "24 October 2002"
    },
    {
        "name": "Flash Assailant",
        "passcode": 96890582,
        "wikilink": "https://yugipedia.com/wiki/MRL-082",
        "set_number": "MRL-082",
        "rarity": "Common",
        "date_release": "24 October 2002"
    },
    {
        "name": "Karate Man",
        "passcode": 23289281,
        "wikilink": "https://yugipedia.com/wiki/MRL-083",
        "set_number": "MRL-083",
        "rarity": "Rare",
        "date_release": "24 October 2002"
    },
    {
        "name": "Dark Zebra",
        "passcode": 59784896,
        "wikilink": "https://yugipedia.com/wiki/MRL-084",
        "set_number": "MRL-084",
        "rarity": "Common",
        "date_release": "24 October 2002"
    },
    {
        "name": "Giant Germ",
        "passcode": 95178994,
        "wikilink": "https://yugipedia.com/wiki/MRL-085",
        "set_number": "MRL-085",
        "rarity": "Rare",
        "date_release": "24 October 2002"
    },
    {
        "name": "Nimble Momonga",
        "passcode": 22567609,
        "wikilink": "https://yugipedia.com/wiki/MRL-086",
        "set_number": "MRL-086",
        "rarity": "Rare",
        "date_release": "24 October 2002"
    },
    {
        "name": "Spear Cretin",
        "passcode": 58551308,
        "wikilink": "https://yugipedia.com/wiki/MRL-087",
        "set_number": "MRL-087",
        "rarity": "Common",
        "date_release": "24 October 2002"
    },
    {
        "name": "Shining Angel",
        "passcode": 95956346,
        "wikilink": "https://yugipedia.com/wiki/MRL-088",
        "set_number": "MRL-088",
        "rarity": "Rare",
        "date_release": "24 October 2002"
    },
    {
        "name": "Boar Soldier",
        "passcode": 21340051,
        "wikilink": "https://yugipedia.com/wiki/MRL-089",
        "set_number": "MRL-089",
        "rarity": "Common",
        "date_release": "24 October 2002"
    },
    {
        "name": "Mother Grizzly",
        "passcode": 57839750,
        "wikilink": "https://yugipedia.com/wiki/MRL-090",
        "set_number": "MRL-090",
        "rarity": "Rare",
        "date_release": "24 October 2002"
    },
    {
        "name": "Flying Kamakiri 1",
        "passcode": 84834865,
        "wikilink": "https://yugipedia.com/wiki/MRL-091",
        "set_number": "MRL-091",
        "rarity": "Rare",
        "date_release": "24 October 2002"
    },
    {
        "name": "Ceremonial Bell",
        "passcode": 20228463,
        "wikilink": "https://yugipedia.com/wiki/MRL-092",
        "set_number": "MRL-092",
        "rarity": "Common",
        "date_release": "24 October 2002"
    },
    {
        "name": "Sonic Bird",
        "passcode": 57617178,
        "wikilink": "https://yugipedia.com/wiki/MRL-093",
        "set_number": "MRL-093",
        "rarity": "Common",
        "date_release": "24 October 2002"
    },
    {
        "name": "Mystic Tomato",
        "passcode": 83011277,
        "wikilink": "https://yugipedia.com/wiki/MRL-094",
        "set_number": "MRL-094",
        "rarity": "Rare",
        "date_release": "24 October 2002"
    },
    {
        "name": "Kotodama",
        "passcode": 19406822,
        "wikilink": "https://yugipedia.com/wiki/MRL-095",
        "set_number": "MRL-095",
        "rarity": "Common",
        "date_release": "24 October 2002"
    },
    {
        "name": "Gaia Power",
        "passcode": 56594520,
        "wikilink": "https://yugipedia.com/wiki/MRL-096",
        "set_number": "MRL-096",
        "rarity": "Normal Rare",
        "date_release": "24 October 2002"
    },
    {
        "name": "Umiiruka",
        "passcode": 82999629,
        "wikilink": "https://yugipedia.com/wiki/MRL-097",
        "set_number": "MRL-097",
        "rarity": "Normal Rare",
        "date_release": "24 October 2002"
    },
    {
        "name": "Molten Destruction",
        "passcode": 19384334,
        "wikilink": "https://yugipedia.com/wiki/MRL-098",
        "set_number": "MRL-098",
        "rarity": "Normal Rare",
        "date_release": "24 October 2002"
    },
    {
        "name": "Rising Air Current",
        "passcode": 45778932,
        "wikilink": "https://yugipedia.com/wiki/MRL-099",
        "set_number": "MRL-099",
        "rarity": "Normal Rare",
        "date_release": "24 October 2002"
    },
    {
        "name": "Luminous Spark",
        "passcode": 81777047,
        "wikilink": "https://yugipedia.com/wiki/MRL-100",
        "set_number": "MRL-100",
        "rarity": "Normal Rare",
        "date_release": "24 October 2002"
    },
    {
        "name": "Mystic Plasma Zone",
        "passcode": 18161786,
        "wikilink": "https://yugipedia.com/wiki/MRL-101",
        "set_number": "MRL-101",
        "rarity": "Common",
        "date_release": "24 October 2002"
    },
    {
        "name": "Messenger of Peace",
        "passcode": 44656491,
        "wikilink": "https://yugipedia.com/wiki/MRL-102",
        "set_number": "MRL-102",
        "rarity": "Super Rare",
        "date_release": "24 October 2002"
    },
    {
        "name": "Serpent Night Dragon",
        "passcode": 66516792,
        "wikilink": "https://yugipedia.com/wiki/MRL-103",
        "set_number": "MRL-103",
        "rarity": "Secret Rare",
        "date_release": "24 October 2002"
    }
]